<?xml version="1.0" encoding="UTF-8"?>
<beans xmlns="http://www.springframework.org/schema/beans"
       xmlns:xsi="http://www.w3.org/2001/XMLSchema-instance"
       xsi:schemaLocation="http://www.springframework.org/schema/beans http://www.springframework.org/schema/beans/spring-beans.xsd">

	<bean id="1" class="com.kamilradzyminski.projekt.domain.Person">
		<constructor-arg name="id" value="1"/>
		<constructor-arg name="firstName" value="Brett"/>
		<constructor-arg name="lastName" value="Hogbourne"/>
		<constructor-arg name="email" value="bhogbourne0@sakura.ne.jp"/>
		<constructor-arg name="gender" value="Female"/>
		<constructor-arg name="creditCardType" value="americanexpress"/>
		<constructor-arg name="creditCardNumber" value="374283959709510"/>
	</bean>
	<bean id="2" class="com.kamilradzyminski.projekt.domain.Person">
		<constructor-arg name="id" value="2"/>
		<constructor-arg name="firstName" value="Antonius"/>
		<constructor-arg name="lastName" value="Hiland"/>
		<constructor-arg name="email" value="ahiland1@amazon.co.jp"/>
		<constructor-arg name="gender" value="Male"/>
		<constructor-arg name="creditCardType" value="jcb"/>
		<constructor-arg name="creditCardNumber" value="3532717819771668"/>
	</bean>
	<bean id="3" class="com.kamilradzyminski.projekt.domain.Person">
		<constructor-arg name="id" value="3"/>
		<constructor-arg name="firstName" value="Ethelda"/>
		<constructor-arg name="lastName" value="De Bischof"/>
		<constructor-arg name="email" value="edebischof2@about.me"/>
		<constructor-arg name="gender" value="Female"/>
		<constructor-arg name="creditCardType" value="switch"/>
		<constructor-arg name="creditCardNumber" value="5641827599792769927"/>
	</bean>
	<bean id="4" class="com.kamilradzyminski.projekt.domain.Person">
		<constructor-arg name="id" value="4"/>
		<constructor-arg name="firstName" value="Hube"/>
		<constructor-arg name="lastName" value="Chanders"/>
		<constructor-arg name="email" value="hchanders3@github.io"/>
		<constructor-arg name="gender" value="Male"/>
		<constructor-arg name="creditCardType" value="jcb"/>
		<constructor-arg name="creditCardNumber" value="3533230619537387"/>
	</bean>
	<bean id="5" class="com.kamilradzyminski.projekt.domain.Person">
		<constructor-arg name="id" value="5"/>
		<constructor-arg name="firstName" value="Jerald"/>
		<constructor-arg name="lastName" value="Jansky"/>
		<constructor-arg name="email" value="jjansky4@histats.com"/>
		<constructor-arg name="gender" value="Male"/>
		<constructor-arg name="creditCardType" value="jcb"/>
		<constructor-arg name="creditCardNumber" value="3572276506050846"/>
	</bean>
	<bean id="6" class="com.kamilradzyminski.projekt.domain.Person">
		<constructor-arg name="id" value="6"/>
		<constructor-arg name="firstName" value="Minni"/>
		<constructor-arg name="lastName" value="Seleway"/>
		<constructor-arg name="email" value="mseleway5@nasa.gov"/>
		<constructor-arg name="gender" value="Female"/>
		<constructor-arg name="creditCardType" value="jcb"/>
		<constructor-arg name="creditCardNumber" value="3557268768039905"/>
	</bean>
	<bean id="7" class="com.kamilradzyminski.projekt.domain.Person">
		<constructor-arg name="id" value="7"/>
		<constructor-arg name="firstName" value="Abbe"/>
		<constructor-arg name="lastName" value="Mohammad"/>
		<constructor-arg name="email" value="amohammad6@oaic.gov.au"/>
		<constructor-arg name="gender" value="Female"/>
		<constructor-arg name="creditCardType" value="diners-club-carte-blanche"/>
		<constructor-arg name="creditCardNumber" value="30254033683415"/>
	</bean>
	<bean id="8" class="com.kamilradzyminski.projekt.domain.Person">
		<constructor-arg name="id" value="8"/>
		<constructor-arg name="firstName" value="Cly"/>
		<constructor-arg name="lastName" value="Shilstone"/>
		<constructor-arg name="email" value="cshilstone7@nyu.edu"/>
		<constructor-arg name="gender" value="Male"/>
		<constructor-arg name="creditCardType" value="jcb"/>
		<constructor-arg name="creditCardNumber" value="3574571515182566"/>
	</bean>
	<bean id="9" class="com.kamilradzyminski.projekt.domain.Person">
		<constructor-arg name="id" value="9"/>
		<constructor-arg name="firstName" value="Eldin"/>
		<constructor-arg name="lastName" value="Ayerst"/>
		<constructor-arg name="email" value="eayerst8@unc.edu"/>
		<constructor-arg name="gender" value="Male"/>
		<constructor-arg name="creditCardType" value="mastercard"/>
		<constructor-arg name="creditCardNumber" value="5010123753811154"/>
	</bean>
	<bean id="10" class="com.kamilradzyminski.projekt.domain.Person">
		<constructor-arg name="id" value="10"/>
		<constructor-arg name="firstName" value="Jervis"/>
		<constructor-arg name="lastName" value="Rykert"/>
		<constructor-arg name="email" value="jrykert9@blogs.com"/>
		<constructor-arg name="gender" value="Male"/>
		<constructor-arg name="creditCardType" value="jcb"/>
		<constructor-arg name="creditCardNumber" value="3565139904600886"/>
	</bean>
	<bean id="11" class="com.kamilradzyminski.projekt.domain.Person">
		<constructor-arg name="id" value="11"/>
		<constructor-arg name="firstName" value="Max"/>
		<constructor-arg name="lastName" value="Devonald"/>
		<constructor-arg name="email" value="mdevonalda@chronoengine.com"/>
		<constructor-arg name="gender" value="Female"/>
		<constructor-arg name="creditCardType" value="americanexpress"/>
		<constructor-arg name="creditCardNumber" value="374288276054615"/>
	</bean>
	<bean id="12" class="com.kamilradzyminski.projekt.domain.Person">
		<constructor-arg name="id" value="12"/>
		<constructor-arg name="firstName" value="Augusto"/>
		<constructor-arg name="lastName" value="Gebhard"/>
		<constructor-arg name="email" value="agebhardb@163.com"/>
		<constructor-arg name="gender" value="Male"/>
		<constructor-arg name="creditCardType" value="jcb"/>
		<constructor-arg name="creditCardNumber" value="3589438574328618"/>
	</bean>
	<bean id="13" class="com.kamilradzyminski.projekt.domain.Person">
		<constructor-arg name="id" value="13"/>
		<constructor-arg name="firstName" value="Luise"/>
		<constructor-arg name="lastName" value="Genders"/>
		<constructor-arg name="email" value="lgendersc@intel.com"/>
		<constructor-arg name="gender" value="Female"/>
		<constructor-arg name="creditCardType" value="jcb"/>
		<constructor-arg name="creditCardNumber" value="3564009660503627"/>
	</bean>
	<bean id="14" class="com.kamilradzyminski.projekt.domain.Person">
		<constructor-arg name="id" value="14"/>
		<constructor-arg name="firstName" value="Nike"/>
		<constructor-arg name="lastName" value="Davidoff"/>
		<constructor-arg name="email" value="ndavidoffd@usda.gov"/>
		<constructor-arg name="gender" value="Female"/>
		<constructor-arg name="creditCardType" value="jcb"/>
		<constructor-arg name="creditCardNumber" value="3570626274697420"/>
	</bean>
	<bean id="15" class="com.kamilradzyminski.projekt.domain.Person">
		<constructor-arg name="id" value="15"/>
		<constructor-arg name="firstName" value="Irita"/>
		<constructor-arg name="lastName" value="Clowsley"/>
		<constructor-arg name="email" value="iclowsleye@multiply.com"/>
		<constructor-arg name="gender" value="Female"/>
		<constructor-arg name="creditCardType" value="maestro"/>
		<constructor-arg name="creditCardNumber" value="6763485687174997457"/>
	</bean>
	<bean id="16" class="com.kamilradzyminski.projekt.domain.Person">
		<constructor-arg name="id" value="16"/>
		<constructor-arg name="firstName" value="Barny"/>
		<constructor-arg name="lastName" value="Swinburne"/>
		<constructor-arg name="email" value="bswinburnef@xrea.com"/>
		<constructor-arg name="gender" value="Male"/>
		<constructor-arg name="creditCardType" value="maestro"/>
		<constructor-arg name="creditCardNumber" value="6759426623326201"/>
	</bean>
	<bean id="17" class="com.kamilradzyminski.projekt.domain.Person">
		<constructor-arg name="id" value="17"/>
		<constructor-arg name="firstName" value="Mathilda"/>
		<constructor-arg name="lastName" value="Loutheane"/>
		<constructor-arg name="email" value="mloutheaneg@netscape.com"/>
		<constructor-arg name="gender" value="Female"/>
		<constructor-arg name="creditCardType" value="mastercard"/>
		<constructor-arg name="creditCardNumber" value="5117908863000926"/>
	</bean>
	<bean id="18" class="com.kamilradzyminski.projekt.domain.Person">
		<constructor-arg name="id" value="18"/>
		<constructor-arg name="firstName" value="Raphaela"/>
		<constructor-arg name="lastName" value="Seggie"/>
		<constructor-arg name="email" value="rseggieh@xrea.com"/>
		<constructor-arg name="gender" value="Female"/>
		<constructor-arg name="creditCardType" value="laser"/>
		<constructor-arg name="creditCardNumber" value="6771786709344244"/>
	</bean>
	<bean id="19" class="com.kamilradzyminski.projekt.domain.Person">
		<constructor-arg name="id" value="19"/>
		<constructor-arg name="firstName" value="Ofelia"/>
		<constructor-arg name="lastName" value="Skerm"/>
		<constructor-arg name="email" value="oskermi@yellowbook.com"/>
		<constructor-arg name="gender" value="Female"/>
		<constructor-arg name="creditCardType" value="jcb"/>
		<constructor-arg name="creditCardNumber" value="3580444047056918"/>
	</bean>
	<bean id="20" class="com.kamilradzyminski.projekt.domain.Person">
		<constructor-arg name="id" value="20"/>
		<constructor-arg name="firstName" value="Hallsy"/>
		<constructor-arg name="lastName" value="Neesam"/>
		<constructor-arg name="email" value="hneesamj@qq.com"/>
		<constructor-arg name="gender" value="Male"/>
		<constructor-arg name="creditCardType" value="visa-electron"/>
		<constructor-arg name="creditCardNumber" value="4844954514191592"/>
	</bean>
	<bean id="21" class="com.kamilradzyminski.projekt.domain.Person">
		<constructor-arg name="id" value="21"/>
		<constructor-arg name="firstName" value="Joachim"/>
		<constructor-arg name="lastName" value="Rannald"/>
		<constructor-arg name="email" value="jrannaldk@360.cn"/>
		<constructor-arg name="gender" value="Male"/>
		<constructor-arg name="creditCardType" value="visa"/>
		<constructor-arg name="creditCardNumber" value="4041370894229988"/>
	</bean>
	<bean id="22" class="com.kamilradzyminski.projekt.domain.Person">
		<constructor-arg name="id" value="22"/>
		<constructor-arg name="firstName" value="Clayton"/>
		<constructor-arg name="lastName" value="Andreazzi"/>
		<constructor-arg name="email" value="candreazzil@usgs.gov"/>
		<constructor-arg name="gender" value="Male"/>
		<constructor-arg name="creditCardType" value="maestro"/>
		<constructor-arg name="creditCardNumber" value="6304601113521168678"/>
	</bean>
	<bean id="23" class="com.kamilradzyminski.projekt.domain.Person">
		<constructor-arg name="id" value="23"/>
		<constructor-arg name="firstName" value="Doy"/>
		<constructor-arg name="lastName" value="Allabarton"/>
		<constructor-arg name="email" value="dallabartonm@free.fr"/>
		<constructor-arg name="gender" value="Male"/>
		<constructor-arg name="creditCardType" value="jcb"/>
		<constructor-arg name="creditCardNumber" value="3575557759050535"/>
	</bean>
	<bean id="24" class="com.kamilradzyminski.projekt.domain.Person">
		<constructor-arg name="id" value="24"/>
		<constructor-arg name="firstName" value="Farrel"/>
		<constructor-arg name="lastName" value="Edgehill"/>
		<constructor-arg name="email" value="fedgehilln@vkontakte.ru"/>
		<constructor-arg name="gender" value="Male"/>
		<constructor-arg name="creditCardType" value="jcb"/>
		<constructor-arg name="creditCardNumber" value="3542036170609245"/>
	</bean>
	<bean id="25" class="com.kamilradzyminski.projekt.domain.Person">
		<constructor-arg name="id" value="25"/>
		<constructor-arg name="firstName" value="Cindie"/>
		<constructor-arg name="lastName" value="Riepl"/>
		<constructor-arg name="email" value="crieplo@dagondesign.com"/>
		<constructor-arg name="gender" value="Female"/>
		<constructor-arg name="creditCardType" value="jcb"/>
		<constructor-arg name="creditCardNumber" value="3577847224805789"/>
	</bean>
	<bean id="26" class="com.kamilradzyminski.projekt.domain.Person">
		<constructor-arg name="id" value="26"/>
		<constructor-arg name="firstName" value="Gwenni"/>
		<constructor-arg name="lastName" value="Rankin"/>
		<constructor-arg name="email" value="grankinp@yelp.com"/>
		<constructor-arg name="gender" value="Female"/>
		<constructor-arg name="creditCardType" value="diners-club-carte-blanche"/>
		<constructor-arg name="creditCardNumber" value="30367713241260"/>
	</bean>
	<bean id="27" class="com.kamilradzyminski.projekt.domain.Person">
		<constructor-arg name="id" value="27"/>
		<constructor-arg name="firstName" value="Orelle"/>
		<constructor-arg name="lastName" value="Walshaw"/>
		<constructor-arg name="email" value="owalshawq@purevolume.com"/>
		<constructor-arg name="gender" value="Female"/>
		<constructor-arg name="creditCardType" value="jcb"/>
		<constructor-arg name="creditCardNumber" value="3575447134553181"/>
	</bean>
	<bean id="28" class="com.kamilradzyminski.projekt.domain.Person">
		<constructor-arg name="id" value="28"/>
		<constructor-arg name="firstName" value="Alberto"/>
		<constructor-arg name="lastName" value="Flux"/>
		<constructor-arg name="email" value="afluxr@sitemeter.com"/>
		<constructor-arg name="gender" value="Male"/>
		<constructor-arg name="creditCardType" value="diners-club-us-ca"/>
		<constructor-arg name="creditCardNumber" value="5477416313234925"/>
	</bean>
	<bean id="29" class="com.kamilradzyminski.projekt.domain.Person">
		<constructor-arg name="id" value="29"/>
		<constructor-arg name="firstName" value="Stormi"/>
		<constructor-arg name="lastName" value="Marriage"/>
		<constructor-arg name="email" value="smarriages@nyu.edu"/>
		<constructor-arg name="gender" value="Female"/>
		<constructor-arg name="creditCardType" value="maestro"/>
		<constructor-arg name="creditCardNumber" value="67621641965611428"/>
	</bean>
	<bean id="30" class="com.kamilradzyminski.projekt.domain.Person">
		<constructor-arg name="id" value="30"/>
		<constructor-arg name="firstName" value="Rheta"/>
		<constructor-arg name="lastName" value="Getcliffe"/>
		<constructor-arg name="email" value="rgetcliffet@mail.ru"/>
		<constructor-arg name="gender" value="Female"/>
		<constructor-arg name="creditCardType" value="jcb"/>
		<constructor-arg name="creditCardNumber" value="3548641069573115"/>
	</bean>
	<bean id="31" class="com.kamilradzyminski.projekt.domain.Person">
		<constructor-arg name="id" value="31"/>
		<constructor-arg name="firstName" value="Annamaria"/>
		<constructor-arg name="lastName" value="Manz"/>
		<constructor-arg name="email" value="amanzu@princeton.edu"/>
		<constructor-arg name="gender" value="Female"/>
		<constructor-arg name="creditCardType" value="maestro"/>
		<constructor-arg name="creditCardNumber" value="50385554494816719"/>
	</bean>
	<bean id="32" class="com.kamilradzyminski.projekt.domain.Person">
		<constructor-arg name="id" value="32"/>
		<constructor-arg name="firstName" value="Marika"/>
		<constructor-arg name="lastName" value="Van Weedenburg"/>
		<constructor-arg name="email" value="mvanweedenburgv@bbc.co.uk"/>
		<constructor-arg name="gender" value="Female"/>
		<constructor-arg name="creditCardType" value="americanexpress"/>
		<constructor-arg name="creditCardNumber" value="374626007338460"/>
	</bean>
	<bean id="33" class="com.kamilradzyminski.projekt.domain.Person">
		<constructor-arg name="id" value="33"/>
		<constructor-arg name="firstName" value="Aloysia"/>
		<constructor-arg name="lastName" value="Orwell"/>
		<constructor-arg name="email" value="aorwellw@intel.com"/>
		<constructor-arg name="gender" value="Female"/>
		<constructor-arg name="creditCardType" value="china-unionpay"/>
		<constructor-arg name="creditCardNumber" value="5602211008535019"/>
	</bean>
	<bean id="34" class="com.kamilradzyminski.projekt.domain.Person">
		<constructor-arg name="id" value="34"/>
		<constructor-arg name="firstName" value="Edyth"/>
		<constructor-arg name="lastName" value="Jahn"/>
		<constructor-arg name="email" value="ejahnx@prweb.com"/>
		<constructor-arg name="gender" value="Female"/>
		<constructor-arg name="creditCardType" value="jcb"/>
		<constructor-arg name="creditCardNumber" value="3559493949082453"/>
	</bean>
	<bean id="35" class="com.kamilradzyminski.projekt.domain.Person">
		<constructor-arg name="id" value="35"/>
		<constructor-arg name="firstName" value="Aylmar"/>
		<constructor-arg name="lastName" value="Yankeev"/>
		<constructor-arg name="email" value="ayankeevy@csmonitor.com"/>
		<constructor-arg name="gender" value="Male"/>
		<constructor-arg name="creditCardType" value="jcb"/>
		<constructor-arg name="creditCardNumber" value="3563648933518556"/>
	</bean>
	<bean id="36" class="com.kamilradzyminski.projekt.domain.Person">
		<constructor-arg name="id" value="36"/>
		<constructor-arg name="firstName" value="Dulce"/>
		<constructor-arg name="lastName" value="Libri"/>
		<constructor-arg name="email" value="dlibriz@thetimes.co.uk"/>
		<constructor-arg name="gender" value="Female"/>
		<constructor-arg name="creditCardType" value="maestro"/>
		<constructor-arg name="creditCardNumber" value="6762368320765286874"/>
	</bean>
	<bean id="37" class="com.kamilradzyminski.projekt.domain.Person">
		<constructor-arg name="id" value="37"/>
		<constructor-arg name="firstName" value="Graham"/>
		<constructor-arg name="lastName" value="Edridge"/>
		<constructor-arg name="email" value="gedridge10@canalblog.com"/>
		<constructor-arg name="gender" value="Male"/>
		<constructor-arg name="creditCardType" value="bankcard"/>
		<constructor-arg name="creditCardNumber" value="5602226255187868"/>
	</bean>
	<bean id="38" class="com.kamilradzyminski.projekt.domain.Person">
		<constructor-arg name="id" value="38"/>
		<constructor-arg name="firstName" value="Jasmin"/>
		<constructor-arg name="lastName" value="Keenlyside"/>
		<constructor-arg name="email" value="jkeenlyside11@imgur.com"/>
		<constructor-arg name="gender" value="Female"/>
		<constructor-arg name="creditCardType" value="switch"/>
		<constructor-arg name="creditCardNumber" value="6759635899647567"/>
	</bean>
	<bean id="39" class="com.kamilradzyminski.projekt.domain.Person">
		<constructor-arg name="id" value="39"/>
		<constructor-arg name="firstName" value="Dode"/>
		<constructor-arg name="lastName" value="Maharry"/>
		<constructor-arg name="email" value="dmaharry12@rediff.com"/>
		<constructor-arg name="gender" value="Female"/>
		<constructor-arg name="creditCardType" value="switch"/>
		<constructor-arg name="creditCardNumber" value="6331105080107809427"/>
	</bean>
	<bean id="40" class="com.kamilradzyminski.projekt.domain.Person">
		<constructor-arg name="id" value="40"/>
		<constructor-arg name="firstName" value="Deane"/>
		<constructor-arg name="lastName" value="Sloat"/>
		<constructor-arg name="email" value="dsloat13@omniture.com"/>
		<constructor-arg name="gender" value="Female"/>
		<constructor-arg name="creditCardType" value="jcb"/>
		<constructor-arg name="creditCardNumber" value="3544402096326678"/>
	</bean>
	<bean id="41" class="com.kamilradzyminski.projekt.domain.Person">
		<constructor-arg name="id" value="41"/>
		<constructor-arg name="firstName" value="Shaylah"/>
		<constructor-arg name="lastName" value="Mallya"/>
		<constructor-arg name="email" value="smallya14@about.me"/>
		<constructor-arg name="gender" value="Female"/>
		<constructor-arg name="creditCardType" value="switch"/>
		<constructor-arg name="creditCardNumber" value="4905266335616434"/>
	</bean>
	<bean id="42" class="com.kamilradzyminski.projekt.domain.Person">
		<constructor-arg name="id" value="42"/>
		<constructor-arg name="firstName" value="Frasquito"/>
		<constructor-arg name="lastName" value="Wordsworth"/>
		<constructor-arg name="email" value="fwordsworth15@ca.gov"/>
		<constructor-arg name="gender" value="Male"/>
		<constructor-arg name="creditCardType" value="diners-club-enroute"/>
		<constructor-arg name="creditCardNumber" value="201898975917554"/>
	</bean>
	<bean id="43" class="com.kamilradzyminski.projekt.domain.Person">
		<constructor-arg name="id" value="43"/>
		<constructor-arg name="firstName" value="Wolf"/>
		<constructor-arg name="lastName" value="Genever"/>
		<constructor-arg name="email" value="wgenever16@yolasite.com"/>
		<constructor-arg name="gender" value="Male"/>
		<constructor-arg name="creditCardType" value="maestro"/>
		<constructor-arg name="creditCardNumber" value="6761818208322629"/>
	</bean>
	<bean id="44" class="com.kamilradzyminski.projekt.domain.Person">
		<constructor-arg name="id" value="44"/>
		<constructor-arg name="firstName" value="Ethan"/>
		<constructor-arg name="lastName" value="Oley"/>
		<constructor-arg name="email" value="eoley17@engadget.com"/>
		<constructor-arg name="gender" value="Male"/>
		<constructor-arg name="creditCardType" value="mastercard"/>
		<constructor-arg name="creditCardNumber" value="5010122117030972"/>
	</bean>
	<bean id="45" class="com.kamilradzyminski.projekt.domain.Person">
		<constructor-arg name="id" value="45"/>
		<constructor-arg name="firstName" value="Gabey"/>
		<constructor-arg name="lastName" value="Lambart"/>
		<constructor-arg name="email" value="glambart18@usnews.com"/>
		<constructor-arg name="gender" value="Female"/>
		<constructor-arg name="creditCardType" value="jcb"/>
		<constructor-arg name="creditCardNumber" value="3562521145804661"/>
	</bean>
	<bean id="46" class="com.kamilradzyminski.projekt.domain.Person">
		<constructor-arg name="id" value="46"/>
		<constructor-arg name="firstName" value="Barrett"/>
		<constructor-arg name="lastName" value="Restill"/>
		<constructor-arg name="email" value="brestill19@timesonline.co.uk"/>
		<constructor-arg name="gender" value="Male"/>
		<constructor-arg name="creditCardType" value="jcb"/>
		<constructor-arg name="creditCardNumber" value="3538163589638429"/>
	</bean>
	<bean id="47" class="com.kamilradzyminski.projekt.domain.Person">
		<constructor-arg name="id" value="47"/>
		<constructor-arg name="firstName" value="Lionello"/>
		<constructor-arg name="lastName" value="Lamminam"/>
		<constructor-arg name="email" value="llamminam1a@hostgator.com"/>
		<constructor-arg name="gender" value="Male"/>
		<constructor-arg name="creditCardType" value="china-unionpay"/>
		<constructor-arg name="creditCardNumber" value="56022540571901884"/>
	</bean>
	<bean id="48" class="com.kamilradzyminski.projekt.domain.Person">
		<constructor-arg name="id" value="48"/>
		<constructor-arg name="firstName" value="Maggi"/>
		<constructor-arg name="lastName" value="Olpin"/>
		<constructor-arg name="email" value="molpin1b@nature.com"/>
		<constructor-arg name="gender" value="Female"/>
		<constructor-arg name="creditCardType" value="solo"/>
		<constructor-arg name="creditCardNumber" value="6334394433606267346"/>
	</bean>
	<bean id="49" class="com.kamilradzyminski.projekt.domain.Person">
		<constructor-arg name="id" value="49"/>
		<constructor-arg name="firstName" value="Nicolina"/>
		<constructor-arg name="lastName" value="Durant"/>
		<constructor-arg name="email" value="ndurant1c@gnu.org"/>
		<constructor-arg name="gender" value="Female"/>
		<constructor-arg name="creditCardType" value="americanexpress"/>
		<constructor-arg name="creditCardNumber" value="337941310074405"/>
	</bean>
	<bean id="50" class="com.kamilradzyminski.projekt.domain.Person">
		<constructor-arg name="id" value="50"/>
		<constructor-arg name="firstName" value="Sebastiano"/>
		<constructor-arg name="lastName" value="Tench"/>
		<constructor-arg name="email" value="stench1d@freewebs.com"/>
		<constructor-arg name="gender" value="Male"/>
		<constructor-arg name="creditCardType" value="switch"/>
		<constructor-arg name="creditCardNumber" value="633348762280039938"/>
	</bean>
	<bean id="51" class="com.kamilradzyminski.projekt.domain.Person">
		<constructor-arg name="id" value="51"/>
		<constructor-arg name="firstName" value="Danna"/>
		<constructor-arg name="lastName" value="Jerrim"/>
		<constructor-arg name="email" value="djerrim1e@nature.com"/>
		<constructor-arg name="gender" value="Female"/>
		<constructor-arg name="creditCardType" value="jcb"/>
		<constructor-arg name="creditCardNumber" value="3572137711303836"/>
	</bean>
	<bean id="52" class="com.kamilradzyminski.projekt.domain.Person">
		<constructor-arg name="id" value="52"/>
		<constructor-arg name="firstName" value="Mari"/>
		<constructor-arg name="lastName" value="Kaesmans"/>
		<constructor-arg name="email" value="mkaesmans1f@globo.com"/>
		<constructor-arg name="gender" value="Female"/>
		<constructor-arg name="creditCardType" value="americanexpress"/>
		<constructor-arg name="creditCardNumber" value="346519423567751"/>
	</bean>
	<bean id="53" class="com.kamilradzyminski.projekt.domain.Person">
		<constructor-arg name="id" value="53"/>
		<constructor-arg name="firstName" value="Jessamyn"/>
		<constructor-arg name="lastName" value="Marsy"/>
		<constructor-arg name="email" value="jmarsy1g@exblog.jp"/>
		<constructor-arg name="gender" value="Female"/>
		<constructor-arg name="creditCardType" value="china-unionpay"/>
		<constructor-arg name="creditCardNumber" value="560222001658471027"/>
	</bean>
	<bean id="54" class="com.kamilradzyminski.projekt.domain.Person">
		<constructor-arg name="id" value="54"/>
		<constructor-arg name="firstName" value="Arch"/>
		<constructor-arg name="lastName" value="Seignior"/>
		<constructor-arg name="email" value="aseignior1h@pcworld.com"/>
		<constructor-arg name="gender" value="Male"/>
		<constructor-arg name="creditCardType" value="switch"/>
		<constructor-arg name="creditCardNumber" value="4905757924389227"/>
	</bean>
	<bean id="55" class="com.kamilradzyminski.projekt.domain.Person">
		<constructor-arg name="id" value="55"/>
		<constructor-arg name="firstName" value="Marie-ann"/>
		<constructor-arg name="lastName" value="Fist"/>
		<constructor-arg name="email" value="mfist1i@army.mil"/>
		<constructor-arg name="gender" value="Female"/>
		<constructor-arg name="creditCardType" value="bankcard"/>
		<constructor-arg name="creditCardNumber" value="5610784421834391"/>
	</bean>
	<bean id="56" class="com.kamilradzyminski.projekt.domain.Person">
		<constructor-arg name="id" value="56"/>
		<constructor-arg name="firstName" value="Kerstin"/>
		<constructor-arg name="lastName" value="Dach"/>
		<constructor-arg name="email" value="kdach1j@redcross.org"/>
		<constructor-arg name="gender" value="Female"/>
		<constructor-arg name="creditCardType" value="jcb"/>
		<constructor-arg name="creditCardNumber" value="3533757986435894"/>
	</bean>
	<bean id="57" class="com.kamilradzyminski.projekt.domain.Person">
		<constructor-arg name="id" value="57"/>
		<constructor-arg name="firstName" value="Darnell"/>
		<constructor-arg name="lastName" value="Sixsmith"/>
		<constructor-arg name="email" value="dsixsmith1k@sohu.com"/>
		<constructor-arg name="gender" value="Male"/>
		<constructor-arg name="creditCardType" value="china-unionpay"/>
		<constructor-arg name="creditCardNumber" value="5602248776678293601"/>
	</bean>
	<bean id="58" class="com.kamilradzyminski.projekt.domain.Person">
		<constructor-arg name="id" value="58"/>
		<constructor-arg name="firstName" value="Misty"/>
		<constructor-arg name="lastName" value="Leng"/>
		<constructor-arg name="email" value="mleng1l@mtv.com"/>
		<constructor-arg name="gender" value="Female"/>
		<constructor-arg name="creditCardType" value="bankcard"/>
		<constructor-arg name="creditCardNumber" value="5602246057457590"/>
	</bean>
	<bean id="59" class="com.kamilradzyminski.projekt.domain.Person">
		<constructor-arg name="id" value="59"/>
		<constructor-arg name="firstName" value="Berni"/>
		<constructor-arg name="lastName" value="Ricards"/>
		<constructor-arg name="email" value="bricards1m@usa.gov"/>
		<constructor-arg name="gender" value="Female"/>
		<constructor-arg name="creditCardType" value="jcb"/>
		<constructor-arg name="creditCardNumber" value="3582884236596141"/>
	</bean>
	<bean id="60" class="com.kamilradzyminski.projekt.domain.Person">
		<constructor-arg name="id" value="60"/>
		<constructor-arg name="firstName" value="Jerrilee"/>
		<constructor-arg name="lastName" value="McGenis"/>
		<constructor-arg name="email" value="jmcgenis1n@symantec.com"/>
		<constructor-arg name="gender" value="Female"/>
		<constructor-arg name="creditCardType" value="bankcard"/>
		<constructor-arg name="creditCardNumber" value="5602218542065874"/>
	</bean>
	<bean id="61" class="com.kamilradzyminski.projekt.domain.Person">
		<constructor-arg name="id" value="61"/>
		<constructor-arg name="firstName" value="Alysia"/>
		<constructor-arg name="lastName" value="Lightoller"/>
		<constructor-arg name="email" value="alightoller1o@liveinternet.ru"/>
		<constructor-arg name="gender" value="Female"/>
		<constructor-arg name="creditCardType" value="americanexpress"/>
		<constructor-arg name="creditCardNumber" value="344452837540234"/>
	</bean>
	<bean id="62" class="com.kamilradzyminski.projekt.domain.Person">
		<constructor-arg name="id" value="62"/>
		<constructor-arg name="firstName" value="Megan"/>
		<constructor-arg name="lastName" value="McCutcheon"/>
		<constructor-arg name="email" value="mmccutcheon1p@unc.edu"/>
		<constructor-arg name="gender" value="Female"/>
		<constructor-arg name="creditCardType" value="jcb"/>
		<constructor-arg name="creditCardNumber" value="3551568838368341"/>
	</bean>
	<bean id="63" class="com.kamilradzyminski.projekt.domain.Person">
		<constructor-arg name="id" value="63"/>
		<constructor-arg name="firstName" value="Suzette"/>
		<constructor-arg name="lastName" value="Stoodale"/>
		<constructor-arg name="email" value="sstoodale1q@sciencedaily.com"/>
		<constructor-arg name="gender" value="Female"/>
		<constructor-arg name="creditCardType" value="jcb"/>
		<constructor-arg name="creditCardNumber" value="3561557025723358"/>
	</bean>
	<bean id="64" class="com.kamilradzyminski.projekt.domain.Person">
		<constructor-arg name="id" value="64"/>
		<constructor-arg name="firstName" value="Frazier"/>
		<constructor-arg name="lastName" value="Fridlington"/>
		<constructor-arg name="email" value="ffridlington1r@behance.net"/>
		<constructor-arg name="gender" value="Male"/>
		<constructor-arg name="creditCardType" value="jcb"/>
		<constructor-arg name="creditCardNumber" value="3552978834074539"/>
	</bean>
	<bean id="65" class="com.kamilradzyminski.projekt.domain.Person">
		<constructor-arg name="id" value="65"/>
		<constructor-arg name="firstName" value="Gayler"/>
		<constructor-arg name="lastName" value="Drissell"/>
		<constructor-arg name="email" value="gdrissell1s@va.gov"/>
		<constructor-arg name="gender" value="Male"/>
		<constructor-arg name="creditCardType" value="maestro"/>
		<constructor-arg name="creditCardNumber" value="5038339780454945"/>
	</bean>
	<bean id="66" class="com.kamilradzyminski.projekt.domain.Person">
		<constructor-arg name="id" value="66"/>
		<constructor-arg name="firstName" value="Martainn"/>
		<constructor-arg name="lastName" value="Feifer"/>
		<constructor-arg name="email" value="mfeifer1t@shop-pro.jp"/>
		<constructor-arg name="gender" value="Male"/>
		<constructor-arg name="creditCardType" value="mastercard"/>
		<constructor-arg name="creditCardNumber" value="5002359320802496"/>
	</bean>
	<bean id="67" class="com.kamilradzyminski.projekt.domain.Person">
		<constructor-arg name="id" value="67"/>
		<constructor-arg name="firstName" value="Allis"/>
		<constructor-arg name="lastName" value="Greenin"/>
		<constructor-arg name="email" value="agreenin1u@flickr.com"/>
		<constructor-arg name="gender" value="Female"/>
		<constructor-arg name="creditCardType" value="bankcard"/>
		<constructor-arg name="creditCardNumber" value="5602244971204529"/>
	</bean>
	<bean id="68" class="com.kamilradzyminski.projekt.domain.Person">
		<constructor-arg name="id" value="68"/>
		<constructor-arg name="firstName" value="Wesley"/>
		<constructor-arg name="lastName" value="Treversh"/>
		<constructor-arg name="email" value="wtreversh1v@reference.com"/>
		<constructor-arg name="gender" value="Male"/>
		<constructor-arg name="creditCardType" value="bankcard"/>
		<constructor-arg name="creditCardNumber" value="5602253037976475"/>
	</bean>
	<bean id="69" class="com.kamilradzyminski.projekt.domain.Person">
		<constructor-arg name="id" value="69"/>
		<constructor-arg name="firstName" value="Remus"/>
		<constructor-arg name="lastName" value="Gamlin"/>
		<constructor-arg name="email" value="rgamlin1w@nhs.uk"/>
		<constructor-arg name="gender" value="Male"/>
		<constructor-arg name="creditCardType" value="jcb"/>
		<constructor-arg name="creditCardNumber" value="3573062200970490"/>
	</bean>
	<bean id="70" class="com.kamilradzyminski.projekt.domain.Person">
		<constructor-arg name="id" value="70"/>
		<constructor-arg name="firstName" value="Craig"/>
		<constructor-arg name="lastName" value="Danihelka"/>
		<constructor-arg name="email" value="cdanihelka1x@github.io"/>
		<constructor-arg name="gender" value="Male"/>
		<constructor-arg name="creditCardType" value="bankcard"/>
		<constructor-arg name="creditCardNumber" value="5602242866359671"/>
	</bean>
	<bean id="71" class="com.kamilradzyminski.projekt.domain.Person">
		<constructor-arg name="id" value="71"/>
		<constructor-arg name="firstName" value="Nicol"/>
		<constructor-arg name="lastName" value="Ambrogini"/>
		<constructor-arg name="email" value="nambrogini1y@webs.com"/>
		<constructor-arg name="gender" value="Female"/>
		<constructor-arg name="creditCardType" value="visa"/>
		<constructor-arg name="creditCardNumber" value="4041379576572417"/>
	</bean>
	<bean id="72" class="com.kamilradzyminski.projekt.domain.Person">
		<constructor-arg name="id" value="72"/>
		<constructor-arg name="firstName" value="Nicola"/>
		<constructor-arg name="lastName" value="Karolovsky"/>
		<constructor-arg name="email" value="nkarolovsky1z@weebly.com"/>
		<constructor-arg name="gender" value="Male"/>
		<constructor-arg name="creditCardType" value="diners-club-enroute"/>
		<constructor-arg name="creditCardNumber" value="201451326030923"/>
	</bean>
	<bean id="73" class="com.kamilradzyminski.projekt.domain.Person">
		<constructor-arg name="id" value="73"/>
		<constructor-arg name="firstName" value="Dyan"/>
		<constructor-arg name="lastName" value="Heeran"/>
		<constructor-arg name="email" value="dheeran20@deliciousdays.com"/>
		<constructor-arg name="gender" value="Female"/>
		<constructor-arg name="creditCardType" value="diners-club-enroute"/>
		<constructor-arg name="creditCardNumber" value="201598819391251"/>
	</bean>
	<bean id="74" class="com.kamilradzyminski.projekt.domain.Person">
		<constructor-arg name="id" value="74"/>
		<constructor-arg name="firstName" value="Andreas"/>
		<constructor-arg name="lastName" value="Polden"/>
		<constructor-arg name="email" value="apolden21@cdbaby.com"/>
		<constructor-arg name="gender" value="Male"/>
		<constructor-arg name="creditCardType" value="mastercard"/>
		<constructor-arg name="creditCardNumber" value="5010123973316646"/>
	</bean>
	<bean id="75" class="com.kamilradzyminski.projekt.domain.Person">
		<constructor-arg name="id" value="75"/>
		<constructor-arg name="firstName" value="Rudiger"/>
		<constructor-arg name="lastName" value="Whitmell"/>
		<constructor-arg name="email" value="rwhitmell22@loc.gov"/>
		<constructor-arg name="gender" value="Male"/>
		<constructor-arg name="creditCardType" value="china-unionpay"/>
		<constructor-arg name="creditCardNumber" value="5602256373788764637"/>
	</bean>
	<bean id="76" class="com.kamilradzyminski.projekt.domain.Person">
		<constructor-arg name="id" value="76"/>
		<constructor-arg name="firstName" value="Sari"/>
		<constructor-arg name="lastName" value="Schult"/>
		<constructor-arg name="email" value="sschult23@npr.org"/>
		<constructor-arg name="gender" value="Female"/>
		<constructor-arg name="creditCardType" value="mastercard"/>
		<constructor-arg name="creditCardNumber" value="5100179388686172"/>
	</bean>
	<bean id="77" class="com.kamilradzyminski.projekt.domain.Person">
		<constructor-arg name="id" value="77"/>
		<constructor-arg name="firstName" value="Thorndike"/>
		<constructor-arg name="lastName" value="Bowhey"/>
		<constructor-arg name="email" value="tbowhey24@yahoo.com"/>
		<constructor-arg name="gender" value="Male"/>
		<constructor-arg name="creditCardType" value="jcb"/>
		<constructor-arg name="creditCardNumber" value="3562202418217903"/>
	</bean>
	<bean id="78" class="com.kamilradzyminski.projekt.domain.Person">
		<constructor-arg name="id" value="78"/>
		<constructor-arg name="firstName" value="Denney"/>
		<constructor-arg name="lastName" value="Wilkins"/>
		<constructor-arg name="email" value="dwilkins25@nps.gov"/>
		<constructor-arg name="gender" value="Male"/>
		<constructor-arg name="creditCardType" value="jcb"/>
		<constructor-arg name="creditCardNumber" value="3584395891091938"/>
	</bean>
	<bean id="79" class="com.kamilradzyminski.projekt.domain.Person">
		<constructor-arg name="id" value="79"/>
		<constructor-arg name="firstName" value="Gerek"/>
		<constructor-arg name="lastName" value="Ilem"/>
		<constructor-arg name="email" value="gilem26@is.gd"/>
		<constructor-arg name="gender" value="Male"/>
		<constructor-arg name="creditCardType" value="jcb"/>
		<constructor-arg name="creditCardNumber" value="3584493335683848"/>
	</bean>
	<bean id="80" class="com.kamilradzyminski.projekt.domain.Person">
		<constructor-arg name="id" value="80"/>
		<constructor-arg name="firstName" value="Charlot"/>
		<constructor-arg name="lastName" value="Quartermain"/>
		<constructor-arg name="email" value="cquartermain27@sourceforge.net"/>
		<constructor-arg name="gender" value="Female"/>
		<constructor-arg name="creditCardType" value="diners-club-us-ca"/>
		<constructor-arg name="creditCardNumber" value="5496505922326531"/>
	</bean>
	<bean id="81" class="com.kamilradzyminski.projekt.domain.Person">
		<constructor-arg name="id" value="81"/>
		<constructor-arg name="firstName" value="Ailey"/>
		<constructor-arg name="lastName" value="Defraine"/>
		<constructor-arg name="email" value="adefraine28@imgur.com"/>
		<constructor-arg name="gender" value="Female"/>
		<constructor-arg name="creditCardType" value="diners-club-carte-blanche"/>
		<constructor-arg name="creditCardNumber" value="30169138999153"/>
	</bean>
	<bean id="82" class="com.kamilradzyminski.projekt.domain.Person">
		<constructor-arg name="id" value="82"/>
		<constructor-arg name="firstName" value="Conrade"/>
		<constructor-arg name="lastName" value="Stubbings"/>
		<constructor-arg name="email" value="cstubbings29@acquirethisname.com"/>
		<constructor-arg name="gender" value="Male"/>
		<constructor-arg name="creditCardType" value="mastercard"/>
		<constructor-arg name="creditCardNumber" value="5100141664560703"/>
	</bean>
	<bean id="83" class="com.kamilradzyminski.projekt.domain.Person">
		<constructor-arg name="id" value="83"/>
		<constructor-arg name="firstName" value="Lexis"/>
		<constructor-arg name="lastName" value="Dmitr"/>
		<constructor-arg name="email" value="ldmitr2a@addtoany.com"/>
		<constructor-arg name="gender" value="Female"/>
		<constructor-arg name="creditCardType" value="jcb"/>
		<constructor-arg name="creditCardNumber" value="3536877282500212"/>
	</bean>
	<bean id="84" class="com.kamilradzyminski.projekt.domain.Person">
		<constructor-arg name="id" value="84"/>
		<constructor-arg name="firstName" value="Budd"/>
		<constructor-arg name="lastName" value="Eubank"/>
		<constructor-arg name="email" value="beubank2b@wufoo.com"/>
		<constructor-arg name="gender" value="Male"/>
		<constructor-arg name="creditCardType" value="jcb"/>
		<constructor-arg name="creditCardNumber" value="3583206045128149"/>
	</bean>
	<bean id="85" class="com.kamilradzyminski.projekt.domain.Person">
		<constructor-arg name="id" value="85"/>
		<constructor-arg name="firstName" value="Vinny"/>
		<constructor-arg name="lastName" value="Delap"/>
		<constructor-arg name="email" value="vdelap2c@usda.gov"/>
		<constructor-arg name="gender" value="Female"/>
		<constructor-arg name="creditCardType" value="diners-club-enroute"/>
		<constructor-arg name="creditCardNumber" value="201455904011767"/>
	</bean>
	<bean id="86" class="com.kamilradzyminski.projekt.domain.Person">
		<constructor-arg name="id" value="86"/>
		<constructor-arg name="firstName" value="Barde"/>
		<constructor-arg name="lastName" value="Biggins"/>
		<constructor-arg name="email" value="bbiggins2d@yellowbook.com"/>
		<constructor-arg name="gender" value="Male"/>
		<constructor-arg name="creditCardType" value="bankcard"/>
		<constructor-arg name="creditCardNumber" value="5602218372762327"/>
	</bean>
	<bean id="87" class="com.kamilradzyminski.projekt.domain.Person">
		<constructor-arg name="id" value="87"/>
		<constructor-arg name="firstName" value="Frederique"/>
		<constructor-arg name="lastName" value="Rikkard"/>
		<constructor-arg name="email" value="frikkard2e@pbs.org"/>
		<constructor-arg name="gender" value="Female"/>
		<constructor-arg name="creditCardType" value="diners-club-carte-blanche"/>
		<constructor-arg name="creditCardNumber" value="30195932052162"/>
	</bean>
	<bean id="88" class="com.kamilradzyminski.projekt.domain.Person">
		<constructor-arg name="id" value="88"/>
		<constructor-arg name="firstName" value="Fiann"/>
		<constructor-arg name="lastName" value="Colthard"/>
		<constructor-arg name="email" value="fcolthard2f@nature.com"/>
		<constructor-arg name="gender" value="Female"/>
		<constructor-arg name="creditCardType" value="jcb"/>
		<constructor-arg name="creditCardNumber" value="3555830880661288"/>
	</bean>
	<bean id="89" class="com.kamilradzyminski.projekt.domain.Person">
		<constructor-arg name="id" value="89"/>
		<constructor-arg name="firstName" value="Benton"/>
		<constructor-arg name="lastName" value="Oolahan"/>
		<constructor-arg name="email" value="boolahan2g@nationalgeographic.com"/>
		<constructor-arg name="gender" value="Male"/>
		<constructor-arg name="creditCardType" value="jcb"/>
		<constructor-arg name="creditCardNumber" value="3553487365838998"/>
	</bean>
	<bean id="90" class="com.kamilradzyminski.projekt.domain.Person">
		<constructor-arg name="id" value="90"/>
		<constructor-arg name="firstName" value="Bartolemo"/>
		<constructor-arg name="lastName" value="Coite"/>
		<constructor-arg name="email" value="bcoite2h@noaa.gov"/>
		<constructor-arg name="gender" value="Male"/>
		<constructor-arg name="creditCardType" value="jcb"/>
		<constructor-arg name="creditCardNumber" value="3552531607852688"/>
	</bean>
	<bean id="91" class="com.kamilradzyminski.projekt.domain.Person">
		<constructor-arg name="id" value="91"/>
		<constructor-arg name="firstName" value="Harald"/>
		<constructor-arg name="lastName" value="Duran"/>
		<constructor-arg name="email" value="hduran2i@nps.gov"/>
		<constructor-arg name="gender" value="Male"/>
		<constructor-arg name="creditCardType" value="jcb"/>
		<constructor-arg name="creditCardNumber" value="3573640167983927"/>
	</bean>
	<bean id="92" class="com.kamilradzyminski.projekt.domain.Person">
		<constructor-arg name="id" value="92"/>
		<constructor-arg name="firstName" value="Corinna"/>
		<constructor-arg name="lastName" value="Minillo"/>
		<constructor-arg name="email" value="cminillo2j@fema.gov"/>
		<constructor-arg name="gender" value="Female"/>
		<constructor-arg name="creditCardType" value="jcb"/>
		<constructor-arg name="creditCardNumber" value="3581871237261628"/>
	</bean>
	<bean id="93" class="com.kamilradzyminski.projekt.domain.Person">
		<constructor-arg name="id" value="93"/>
		<constructor-arg name="firstName" value="Ruthie"/>
		<constructor-arg name="lastName" value="Derye-Barrett"/>
		<constructor-arg name="email" value="rderyebarrett2k@tripadvisor.com"/>
		<constructor-arg name="gender" value="Female"/>
		<constructor-arg name="creditCardType" value="diners-club-carte-blanche"/>
		<constructor-arg name="creditCardNumber" value="30409396717222"/>
	</bean>
	<bean id="94" class="com.kamilradzyminski.projekt.domain.Person">
		<constructor-arg name="id" value="94"/>
		<constructor-arg name="firstName" value="Midge"/>
		<constructor-arg name="lastName" value="Cockcroft"/>
		<constructor-arg name="email" value="mcockcroft2l@trellian.com"/>
		<constructor-arg name="gender" value="Female"/>
		<constructor-arg name="creditCardType" value="jcb"/>
		<constructor-arg name="creditCardNumber" value="3563784946191675"/>
	</bean>
	<bean id="95" class="com.kamilradzyminski.projekt.domain.Person">
		<constructor-arg name="id" value="95"/>
		<constructor-arg name="firstName" value="Antons"/>
		<constructor-arg name="lastName" value="Keogh"/>
		<constructor-arg name="email" value="akeogh2m@amazon.co.uk"/>
		<constructor-arg name="gender" value="Male"/>
		<constructor-arg name="creditCardType" value="diners-club-carte-blanche"/>
		<constructor-arg name="creditCardNumber" value="30522883835461"/>
	</bean>
	<bean id="96" class="com.kamilradzyminski.projekt.domain.Person">
		<constructor-arg name="id" value="96"/>
		<constructor-arg name="firstName" value="Paxton"/>
		<constructor-arg name="lastName" value="Headingham"/>
		<constructor-arg name="email" value="pheadingham2n@guardian.co.uk"/>
		<constructor-arg name="gender" value="Male"/>
		<constructor-arg name="creditCardType" value="switch"/>
		<constructor-arg name="creditCardNumber" value="564182799198963888"/>
	</bean>
	<bean id="97" class="com.kamilradzyminski.projekt.domain.Person">
		<constructor-arg name="id" value="97"/>
		<constructor-arg name="firstName" value="Lamond"/>
		<constructor-arg name="lastName" value="Jozefczak"/>
		<constructor-arg name="email" value="ljozefczak2o@wp.com"/>
		<constructor-arg name="gender" value="Male"/>
		<constructor-arg name="creditCardType" value="jcb"/>
		<constructor-arg name="creditCardNumber" value="3562295994590917"/>
	</bean>
	<bean id="98" class="com.kamilradzyminski.projekt.domain.Person">
		<constructor-arg name="id" value="98"/>
		<constructor-arg name="firstName" value="Sukey"/>
		<constructor-arg name="lastName" value="Ridsdole"/>
		<constructor-arg name="email" value="sridsdole2p@imgur.com"/>
		<constructor-arg name="gender" value="Female"/>
		<constructor-arg name="creditCardType" value="diners-club-enroute"/>
		<constructor-arg name="creditCardNumber" value="201431380950505"/>
	</bean>
	<bean id="99" class="com.kamilradzyminski.projekt.domain.Person">
		<constructor-arg name="id" value="99"/>
		<constructor-arg name="firstName" value="Brockie"/>
		<constructor-arg name="lastName" value="Nekrews"/>
		<constructor-arg name="email" value="bnekrews2q@thetimes.co.uk"/>
		<constructor-arg name="gender" value="Male"/>
		<constructor-arg name="creditCardType" value="maestro"/>
		<constructor-arg name="creditCardNumber" value="6304906418192157427"/>
	</bean>
	<bean id="100" class="com.kamilradzyminski.projekt.domain.Person">
		<constructor-arg name="id" value="100"/>
		<constructor-arg name="firstName" value="Giulio"/>
		<constructor-arg name="lastName" value="Thys"/>
		<constructor-arg name="email" value="gthys2r@mayoclinic.com"/>
		<constructor-arg name="gender" value="Male"/>
		<constructor-arg name="creditCardType" value="jcb"/>
		<constructor-arg name="creditCardNumber" value="3578139234780684"/>
	</bean>
	<bean id="101" class="com.kamilradzyminski.projekt.domain.Person">
		<constructor-arg name="id" value="101"/>
		<constructor-arg name="firstName" value="Sutton"/>
		<constructor-arg name="lastName" value="Tyler"/>
		<constructor-arg name="email" value="styler2s@yale.edu"/>
		<constructor-arg name="gender" value="Male"/>
		<constructor-arg name="creditCardType" value="jcb"/>
		<constructor-arg name="creditCardNumber" value="3558869556116794"/>
	</bean>
	<bean id="102" class="com.kamilradzyminski.projekt.domain.Person">
		<constructor-arg name="id" value="102"/>
		<constructor-arg name="firstName" value="Trescha"/>
		<constructor-arg name="lastName" value="Ianson"/>
		<constructor-arg name="email" value="tianson2t@columbia.edu"/>
		<constructor-arg name="gender" value="Female"/>
		<constructor-arg name="creditCardType" value="maestro"/>
		<constructor-arg name="creditCardNumber" value="5018276576823718484"/>
	</bean>
	<bean id="103" class="com.kamilradzyminski.projekt.domain.Person">
		<constructor-arg name="id" value="103"/>
		<constructor-arg name="firstName" value="Vachel"/>
		<constructor-arg name="lastName" value="Stuckley"/>
		<constructor-arg name="email" value="vstuckley2u@alibaba.com"/>
		<constructor-arg name="gender" value="Male"/>
		<constructor-arg name="creditCardType" value="diners-club-carte-blanche"/>
		<constructor-arg name="creditCardNumber" value="30513898760240"/>
	</bean>
	<bean id="104" class="com.kamilradzyminski.projekt.domain.Person">
		<constructor-arg name="id" value="104"/>
		<constructor-arg name="firstName" value="Lammond"/>
		<constructor-arg name="lastName" value="Libbie"/>
		<constructor-arg name="email" value="llibbie2v@blogtalkradio.com"/>
		<constructor-arg name="gender" value="Male"/>
		<constructor-arg name="creditCardType" value="diners-club-carte-blanche"/>
		<constructor-arg name="creditCardNumber" value="30314168083367"/>
	</bean>
	<bean id="105" class="com.kamilradzyminski.projekt.domain.Person">
		<constructor-arg name="id" value="105"/>
		<constructor-arg name="firstName" value="Theo"/>
		<constructor-arg name="lastName" value="Plumptre"/>
		<constructor-arg name="email" value="tplumptre2w@skyrock.com"/>
		<constructor-arg name="gender" value="Female"/>
		<constructor-arg name="creditCardType" value="visa"/>
		<constructor-arg name="creditCardNumber" value="4017959081613"/>
	</bean>
	<bean id="106" class="com.kamilradzyminski.projekt.domain.Person">
		<constructor-arg name="id" value="106"/>
		<constructor-arg name="firstName" value="Erma"/>
		<constructor-arg name="lastName" value="Housbie"/>
		<constructor-arg name="email" value="ehousbie2x@noaa.gov"/>
		<constructor-arg name="gender" value="Female"/>
		<constructor-arg name="creditCardType" value="jcb"/>
		<constructor-arg name="creditCardNumber" value="3586913831279138"/>
	</bean>
	<bean id="107" class="com.kamilradzyminski.projekt.domain.Person">
		<constructor-arg name="id" value="107"/>
		<constructor-arg name="firstName" value="Ogdan"/>
		<constructor-arg name="lastName" value="Breston"/>
		<constructor-arg name="email" value="obreston2y@yahoo.com"/>
		<constructor-arg name="gender" value="Male"/>
		<constructor-arg name="creditCardType" value="jcb"/>
		<constructor-arg name="creditCardNumber" value="3586512232037309"/>
	</bean>
	<bean id="108" class="com.kamilradzyminski.projekt.domain.Person">
		<constructor-arg name="id" value="108"/>
		<constructor-arg name="firstName" value="Tore"/>
		<constructor-arg name="lastName" value="Cordelle"/>
		<constructor-arg name="email" value="tcordelle2z@state.tx.us"/>
		<constructor-arg name="gender" value="Male"/>
		<constructor-arg name="creditCardType" value="diners-club-enroute"/>
		<constructor-arg name="creditCardNumber" value="201695253990752"/>
	</bean>
	<bean id="109" class="com.kamilradzyminski.projekt.domain.Person">
		<constructor-arg name="id" value="109"/>
		<constructor-arg name="firstName" value="Tammi"/>
		<constructor-arg name="lastName" value="Rainbird"/>
		<constructor-arg name="email" value="trainbird30@printfriendly.com"/>
		<constructor-arg name="gender" value="Female"/>
		<constructor-arg name="creditCardType" value="jcb"/>
		<constructor-arg name="creditCardNumber" value="3560650314627926"/>
	</bean>
	<bean id="110" class="com.kamilradzyminski.projekt.domain.Person">
		<constructor-arg name="id" value="110"/>
		<constructor-arg name="firstName" value="Lorry"/>
		<constructor-arg name="lastName" value="Gatecliff"/>
		<constructor-arg name="email" value="lgatecliff31@alibaba.com"/>
		<constructor-arg name="gender" value="Male"/>
		<constructor-arg name="creditCardType" value="solo"/>
		<constructor-arg name="creditCardNumber" value="6334106692538688"/>
	</bean>
	<bean id="111" class="com.kamilradzyminski.projekt.domain.Person">
		<constructor-arg name="id" value="111"/>
		<constructor-arg name="firstName" value="Mallory"/>
		<constructor-arg name="lastName" value="Duester"/>
		<constructor-arg name="email" value="mduester32@sciencedirect.com"/>
		<constructor-arg name="gender" value="Female"/>
		<constructor-arg name="creditCardType" value="mastercard"/>
		<constructor-arg name="creditCardNumber" value="5100149662465379"/>
	</bean>
	<bean id="112" class="com.kamilradzyminski.projekt.domain.Person">
		<constructor-arg name="id" value="112"/>
		<constructor-arg name="firstName" value="Debera"/>
		<constructor-arg name="lastName" value="Hempel"/>
		<constructor-arg name="email" value="dhempel33@examiner.com"/>
		<constructor-arg name="gender" value="Female"/>
		<constructor-arg name="creditCardType" value="switch"/>
		<constructor-arg name="creditCardNumber" value="4905203999225939"/>
	</bean>
	<bean id="113" class="com.kamilradzyminski.projekt.domain.Person">
		<constructor-arg name="id" value="113"/>
		<constructor-arg name="firstName" value="Rafferty"/>
		<constructor-arg name="lastName" value="Hubbins"/>
		<constructor-arg name="email" value="rhubbins34@ning.com"/>
		<constructor-arg name="gender" value="Male"/>
		<constructor-arg name="creditCardType" value="jcb"/>
		<constructor-arg name="creditCardNumber" value="3582619558372915"/>
	</bean>
	<bean id="114" class="com.kamilradzyminski.projekt.domain.Person">
		<constructor-arg name="id" value="114"/>
		<constructor-arg name="firstName" value="Dominick"/>
		<constructor-arg name="lastName" value="Massingberd"/>
		<constructor-arg name="email" value="dmassingberd35@sciencedaily.com"/>
		<constructor-arg name="gender" value="Male"/>
		<constructor-arg name="creditCardType" value="mastercard"/>
		<constructor-arg name="creditCardNumber" value="5002351343338475"/>
	</bean>
	<bean id="115" class="com.kamilradzyminski.projekt.domain.Person">
		<constructor-arg name="id" value="115"/>
		<constructor-arg name="firstName" value="Reyna"/>
		<constructor-arg name="lastName" value="Tooby"/>
		<constructor-arg name="email" value="rtooby36@mayoclinic.com"/>
		<constructor-arg name="gender" value="Female"/>
		<constructor-arg name="creditCardType" value="mastercard"/>
		<constructor-arg name="creditCardNumber" value="5527495111861956"/>
	</bean>
	<bean id="116" class="com.kamilradzyminski.projekt.domain.Person">
		<constructor-arg name="id" value="116"/>
		<constructor-arg name="firstName" value="Mack"/>
		<constructor-arg name="lastName" value="Bicknell"/>
		<constructor-arg name="email" value="mbicknell37@trellian.com"/>
		<constructor-arg name="gender" value="Male"/>
		<constructor-arg name="creditCardType" value="visa-electron"/>
		<constructor-arg name="creditCardNumber" value="4844603351886026"/>
	</bean>
	<bean id="117" class="com.kamilradzyminski.projekt.domain.Person">
		<constructor-arg name="id" value="117"/>
		<constructor-arg name="firstName" value="Emelda"/>
		<constructor-arg name="lastName" value="Coite"/>
		<constructor-arg name="email" value="ecoite38@csmonitor.com"/>
		<constructor-arg name="gender" value="Female"/>
		<constructor-arg name="creditCardType" value="instapayment"/>
		<constructor-arg name="creditCardNumber" value="6388928145867348"/>
	</bean>
	<bean id="118" class="com.kamilradzyminski.projekt.domain.Person">
		<constructor-arg name="id" value="118"/>
		<constructor-arg name="firstName" value="Bart"/>
		<constructor-arg name="lastName" value="Bew"/>
		<constructor-arg name="email" value="bbew39@census.gov"/>
		<constructor-arg name="gender" value="Male"/>
		<constructor-arg name="creditCardType" value="mastercard"/>
		<constructor-arg name="creditCardNumber" value="5100176677353480"/>
	</bean>
	<bean id="119" class="com.kamilradzyminski.projekt.domain.Person">
		<constructor-arg name="id" value="119"/>
		<constructor-arg name="firstName" value="Selby"/>
		<constructor-arg name="lastName" value="Marchent"/>
		<constructor-arg name="email" value="smarchent3a@quantcast.com"/>
		<constructor-arg name="gender" value="Male"/>
		<constructor-arg name="creditCardType" value="jcb"/>
		<constructor-arg name="creditCardNumber" value="3537404798102042"/>
	</bean>
	<bean id="120" class="com.kamilradzyminski.projekt.domain.Person">
		<constructor-arg name="id" value="120"/>
		<constructor-arg name="firstName" value="Kylie"/>
		<constructor-arg name="lastName" value="Aloshechkin"/>
		<constructor-arg name="email" value="kaloshechkin3b@alexa.com"/>
		<constructor-arg name="gender" value="Male"/>
		<constructor-arg name="creditCardType" value="jcb"/>
		<constructor-arg name="creditCardNumber" value="3546083283134949"/>
	</bean>
	<bean id="121" class="com.kamilradzyminski.projekt.domain.Person">
		<constructor-arg name="id" value="121"/>
		<constructor-arg name="firstName" value="Joyann"/>
		<constructor-arg name="lastName" value="McGinty"/>
		<constructor-arg name="email" value="jmcginty3c@yandex.ru"/>
		<constructor-arg name="gender" value="Female"/>
		<constructor-arg name="creditCardType" value="maestro"/>
		<constructor-arg name="creditCardNumber" value="502050209651217482"/>
	</bean>
	<bean id="122" class="com.kamilradzyminski.projekt.domain.Person">
		<constructor-arg name="id" value="122"/>
		<constructor-arg name="firstName" value="Anett"/>
		<constructor-arg name="lastName" value="Boick"/>
		<constructor-arg name="email" value="aboick3d@w3.org"/>
		<constructor-arg name="gender" value="Female"/>
		<constructor-arg name="creditCardType" value="switch"/>
		<constructor-arg name="creditCardNumber" value="633344843991091345"/>
	</bean>
	<bean id="123" class="com.kamilradzyminski.projekt.domain.Person">
		<constructor-arg name="id" value="123"/>
		<constructor-arg name="firstName" value="Roxy"/>
		<constructor-arg name="lastName" value="Joinsey"/>
		<constructor-arg name="email" value="rjoinsey3e@google.pl"/>
		<constructor-arg name="gender" value="Female"/>
		<constructor-arg name="creditCardType" value="switch"/>
		<constructor-arg name="creditCardNumber" value="493638365190014534"/>
	</bean>
	<bean id="124" class="com.kamilradzyminski.projekt.domain.Person">
		<constructor-arg name="id" value="124"/>
		<constructor-arg name="firstName" value="Evyn"/>
		<constructor-arg name="lastName" value="Woodrow"/>
		<constructor-arg name="email" value="ewoodrow3f@vimeo.com"/>
		<constructor-arg name="gender" value="Male"/>
		<constructor-arg name="creditCardType" value="visa-electron"/>
		<constructor-arg name="creditCardNumber" value="4026613336532843"/>
	</bean>
	<bean id="125" class="com.kamilradzyminski.projekt.domain.Person">
		<constructor-arg name="id" value="125"/>
		<constructor-arg name="firstName" value="Aubry"/>
		<constructor-arg name="lastName" value="Maycey"/>
		<constructor-arg name="email" value="amaycey3g@umich.edu"/>
		<constructor-arg name="gender" value="Female"/>
		<constructor-arg name="creditCardType" value="jcb"/>
		<constructor-arg name="creditCardNumber" value="3540882924798863"/>
	</bean>
	<bean id="126" class="com.kamilradzyminski.projekt.domain.Person">
		<constructor-arg name="id" value="126"/>
		<constructor-arg name="firstName" value="Estelle"/>
		<constructor-arg name="lastName" value="Blondell"/>
		<constructor-arg name="email" value="eblondell3h@nps.gov"/>
		<constructor-arg name="gender" value="Female"/>
		<constructor-arg name="creditCardType" value="bankcard"/>
		<constructor-arg name="creditCardNumber" value="5602230281724728"/>
	</bean>
	<bean id="127" class="com.kamilradzyminski.projekt.domain.Person">
		<constructor-arg name="id" value="127"/>
		<constructor-arg name="firstName" value="Leshia"/>
		<constructor-arg name="lastName" value="Wintringham"/>
		<constructor-arg name="email" value="lwintringham3i@craigslist.org"/>
		<constructor-arg name="gender" value="Female"/>
		<constructor-arg name="creditCardType" value="mastercard"/>
		<constructor-arg name="creditCardNumber" value="5010125926501232"/>
	</bean>
	<bean id="128" class="com.kamilradzyminski.projekt.domain.Person">
		<constructor-arg name="id" value="128"/>
		<constructor-arg name="firstName" value="Rafaela"/>
		<constructor-arg name="lastName" value="Lasseter"/>
		<constructor-arg name="email" value="rlasseter3j@earthlink.net"/>
		<constructor-arg name="gender" value="Female"/>
		<constructor-arg name="creditCardType" value="laser"/>
		<constructor-arg name="creditCardNumber" value="630405421531095431"/>
	</bean>
	<bean id="129" class="com.kamilradzyminski.projekt.domain.Person">
		<constructor-arg name="id" value="129"/>
		<constructor-arg name="firstName" value="Ron"/>
		<constructor-arg name="lastName" value="Airs"/>
		<constructor-arg name="email" value="rairs3k@friendfeed.com"/>
		<constructor-arg name="gender" value="Male"/>
		<constructor-arg name="creditCardType" value="visa-electron"/>
		<constructor-arg name="creditCardNumber" value="4175001523476009"/>
	</bean>
	<bean id="130" class="com.kamilradzyminski.projekt.domain.Person">
		<constructor-arg name="id" value="130"/>
		<constructor-arg name="firstName" value="Madeleine"/>
		<constructor-arg name="lastName" value="Murrill"/>
		<constructor-arg name="email" value="mmurrill3l@delicious.com"/>
		<constructor-arg name="gender" value="Female"/>
		<constructor-arg name="creditCardType" value="switch"/>
		<constructor-arg name="creditCardNumber" value="491136410005259758"/>
	</bean>
	<bean id="131" class="com.kamilradzyminski.projekt.domain.Person">
		<constructor-arg name="id" value="131"/>
		<constructor-arg name="firstName" value="Marnia"/>
		<constructor-arg name="lastName" value="Dancer"/>
		<constructor-arg name="email" value="mdancer3m@ehow.com"/>
		<constructor-arg name="gender" value="Female"/>
		<constructor-arg name="creditCardType" value="jcb"/>
		<constructor-arg name="creditCardNumber" value="3581496327438660"/>
	</bean>
	<bean id="132" class="com.kamilradzyminski.projekt.domain.Person">
		<constructor-arg name="id" value="132"/>
		<constructor-arg name="firstName" value="Xylina"/>
		<constructor-arg name="lastName" value="Gilbert"/>
		<constructor-arg name="email" value="xgilbert3n@alexa.com"/>
		<constructor-arg name="gender" value="Female"/>
		<constructor-arg name="creditCardType" value="switch"/>
		<constructor-arg name="creditCardNumber" value="6333350260210317157"/>
	</bean>
	<bean id="133" class="com.kamilradzyminski.projekt.domain.Person">
		<constructor-arg name="id" value="133"/>
		<constructor-arg name="firstName" value="Garik"/>
		<constructor-arg name="lastName" value="Brisland"/>
		<constructor-arg name="email" value="gbrisland3o@blog.com"/>
		<constructor-arg name="gender" value="Male"/>
		<constructor-arg name="creditCardType" value="bankcard"/>
		<constructor-arg name="creditCardNumber" value="5610090147495206"/>
	</bean>
	<bean id="134" class="com.kamilradzyminski.projekt.domain.Person">
		<constructor-arg name="id" value="134"/>
		<constructor-arg name="firstName" value="Corie"/>
		<constructor-arg name="lastName" value="Chastelain"/>
		<constructor-arg name="email" value="cchastelain3p@sitemeter.com"/>
		<constructor-arg name="gender" value="Female"/>
		<constructor-arg name="creditCardType" value="mastercard"/>
		<constructor-arg name="creditCardNumber" value="5108752970188799"/>
	</bean>
	<bean id="135" class="com.kamilradzyminski.projekt.domain.Person">
		<constructor-arg name="id" value="135"/>
		<constructor-arg name="firstName" value="Renaud"/>
		<constructor-arg name="lastName" value="Lansdown"/>
		<constructor-arg name="email" value="rlansdown3q@wp.com"/>
		<constructor-arg name="gender" value="Male"/>
		<constructor-arg name="creditCardType" value="jcb"/>
		<constructor-arg name="creditCardNumber" value="3563171984739138"/>
	</bean>
	<bean id="136" class="com.kamilradzyminski.projekt.domain.Person">
		<constructor-arg name="id" value="136"/>
		<constructor-arg name="firstName" value="Aubrey"/>
		<constructor-arg name="lastName" value="Gotts"/>
		<constructor-arg name="email" value="agotts3r@eventbrite.com"/>
		<constructor-arg name="gender" value="Male"/>
		<constructor-arg name="creditCardType" value="jcb"/>
		<constructor-arg name="creditCardNumber" value="3562277192968509"/>
	</bean>
	<bean id="137" class="com.kamilradzyminski.projekt.domain.Person">
		<constructor-arg name="id" value="137"/>
		<constructor-arg name="firstName" value="Tadd"/>
		<constructor-arg name="lastName" value="Winston"/>
		<constructor-arg name="email" value="twinston3s@e-recht24.de"/>
		<constructor-arg name="gender" value="Male"/>
		<constructor-arg name="creditCardType" value="jcb"/>
		<constructor-arg name="creditCardNumber" value="3528471316973791"/>
	</bean>
	<bean id="138" class="com.kamilradzyminski.projekt.domain.Person">
		<constructor-arg name="id" value="138"/>
		<constructor-arg name="firstName" value="Thain"/>
		<constructor-arg name="lastName" value="Duigenan"/>
		<constructor-arg name="email" value="tduigenan3t@smugmug.com"/>
		<constructor-arg name="gender" value="Male"/>
		<constructor-arg name="creditCardType" value="maestro"/>
		<constructor-arg name="creditCardNumber" value="6762560391972724"/>
	</bean>
	<bean id="139" class="com.kamilradzyminski.projekt.domain.Person">
		<constructor-arg name="id" value="139"/>
		<constructor-arg name="firstName" value="Man"/>
		<constructor-arg name="lastName" value="Cumpton"/>
		<constructor-arg name="email" value="mcumpton3u@i2i.jp"/>
		<constructor-arg name="gender" value="Male"/>
		<constructor-arg name="creditCardType" value="americanexpress"/>
		<constructor-arg name="creditCardNumber" value="372301732182805"/>
	</bean>
	<bean id="140" class="com.kamilradzyminski.projekt.domain.Person">
		<constructor-arg name="id" value="140"/>
		<constructor-arg name="firstName" value="Garek"/>
		<constructor-arg name="lastName" value="Kleinstern"/>
		<constructor-arg name="email" value="gkleinstern3v@sitemeter.com"/>
		<constructor-arg name="gender" value="Male"/>
		<constructor-arg name="creditCardType" value="mastercard"/>
		<constructor-arg name="creditCardNumber" value="5010127256726009"/>
	</bean>
	<bean id="141" class="com.kamilradzyminski.projekt.domain.Person">
		<constructor-arg name="id" value="141"/>
		<constructor-arg name="firstName" value="Evy"/>
		<constructor-arg name="lastName" value="Hallor"/>
		<constructor-arg name="email" value="ehallor3w@seesaa.net"/>
		<constructor-arg name="gender" value="Female"/>
		<constructor-arg name="creditCardType" value="americanexpress"/>
		<constructor-arg name="creditCardNumber" value="374288658804611"/>
	</bean>
	<bean id="142" class="com.kamilradzyminski.projekt.domain.Person">
		<constructor-arg name="id" value="142"/>
		<constructor-arg name="firstName" value="Tracy"/>
		<constructor-arg name="lastName" value="Robjents"/>
		<constructor-arg name="email" value="trobjents3x@washington.edu"/>
		<constructor-arg name="gender" value="Female"/>
		<constructor-arg name="creditCardType" value="mastercard"/>
		<constructor-arg name="creditCardNumber" value="5100139319013839"/>
	</bean>
	<bean id="143" class="com.kamilradzyminski.projekt.domain.Person">
		<constructor-arg name="id" value="143"/>
		<constructor-arg name="firstName" value="Salaidh"/>
		<constructor-arg name="lastName" value="Labbe"/>
		<constructor-arg name="email" value="slabbe3y@bravesites.com"/>
		<constructor-arg name="gender" value="Female"/>
		<constructor-arg name="creditCardType" value="visa-electron"/>
		<constructor-arg name="creditCardNumber" value="4508143894255444"/>
	</bean>
	<bean id="144" class="com.kamilradzyminski.projekt.domain.Person">
		<constructor-arg name="id" value="144"/>
		<constructor-arg name="firstName" value="Trey"/>
		<constructor-arg name="lastName" value="Riche"/>
		<constructor-arg name="email" value="triche3z@csmonitor.com"/>
		<constructor-arg name="gender" value="Male"/>
		<constructor-arg name="creditCardType" value="jcb"/>
		<constructor-arg name="creditCardNumber" value="3558830265643072"/>
	</bean>
	<bean id="145" class="com.kamilradzyminski.projekt.domain.Person">
		<constructor-arg name="id" value="145"/>
		<constructor-arg name="firstName" value="Deck"/>
		<constructor-arg name="lastName" value="Verdey"/>
		<constructor-arg name="email" value="dverdey40@flickr.com"/>
		<constructor-arg name="gender" value="Male"/>
		<constructor-arg name="creditCardType" value="diners-club-enroute"/>
		<constructor-arg name="creditCardNumber" value="201886917323718"/>
	</bean>
	<bean id="146" class="com.kamilradzyminski.projekt.domain.Person">
		<constructor-arg name="id" value="146"/>
		<constructor-arg name="firstName" value="Dominic"/>
		<constructor-arg name="lastName" value="Slimmon"/>
		<constructor-arg name="email" value="dslimmon41@noaa.gov"/>
		<constructor-arg name="gender" value="Male"/>
		<constructor-arg name="creditCardType" value="maestro"/>
		<constructor-arg name="creditCardNumber" value="502073816532208580"/>
	</bean>
	<bean id="147" class="com.kamilradzyminski.projekt.domain.Person">
		<constructor-arg name="id" value="147"/>
		<constructor-arg name="firstName" value="Alverta"/>
		<constructor-arg name="lastName" value="McArtan"/>
		<constructor-arg name="email" value="amcartan42@disqus.com"/>
		<constructor-arg name="gender" value="Female"/>
		<constructor-arg name="creditCardType" value="jcb"/>
		<constructor-arg name="creditCardNumber" value="3553398941473848"/>
	</bean>
	<bean id="148" class="com.kamilradzyminski.projekt.domain.Person">
		<constructor-arg name="id" value="148"/>
		<constructor-arg name="firstName" value="Diane-marie"/>
		<constructor-arg name="lastName" value="Stratiff"/>
		<constructor-arg name="email" value="dstratiff43@is.gd"/>
		<constructor-arg name="gender" value="Female"/>
		<constructor-arg name="creditCardType" value="jcb"/>
		<constructor-arg name="creditCardNumber" value="3565231216752842"/>
	</bean>
	<bean id="149" class="com.kamilradzyminski.projekt.domain.Person">
		<constructor-arg name="id" value="149"/>
		<constructor-arg name="firstName" value="Kimbell"/>
		<constructor-arg name="lastName" value="Izakof"/>
		<constructor-arg name="email" value="kizakof44@ft.com"/>
		<constructor-arg name="gender" value="Male"/>
		<constructor-arg name="creditCardType" value="maestro"/>
		<constructor-arg name="creditCardNumber" value="67620130954176537"/>
	</bean>
	<bean id="150" class="com.kamilradzyminski.projekt.domain.Person">
		<constructor-arg name="id" value="150"/>
		<constructor-arg name="firstName" value="Adolphe"/>
		<constructor-arg name="lastName" value="Blackman"/>
		<constructor-arg name="email" value="ablackman45@booking.com"/>
		<constructor-arg name="gender" value="Male"/>
		<constructor-arg name="creditCardType" value="diners-club-us-ca"/>
		<constructor-arg name="creditCardNumber" value="5518184759969047"/>
	</bean>
	<bean id="151" class="com.kamilradzyminski.projekt.domain.Person">
		<constructor-arg name="id" value="151"/>
		<constructor-arg name="firstName" value="Moshe"/>
		<constructor-arg name="lastName" value="Befroy"/>
		<constructor-arg name="email" value="mbefroy46@sbwire.com"/>
		<constructor-arg name="gender" value="Male"/>
		<constructor-arg name="creditCardType" value="jcb"/>
		<constructor-arg name="creditCardNumber" value="3546584827180678"/>
	</bean>
	<bean id="152" class="com.kamilradzyminski.projekt.domain.Person">
		<constructor-arg name="id" value="152"/>
		<constructor-arg name="firstName" value="Coleman"/>
		<constructor-arg name="lastName" value="Bissill"/>
		<constructor-arg name="email" value="cbissill47@bbb.org"/>
		<constructor-arg name="gender" value="Male"/>
		<constructor-arg name="creditCardType" value="jcb"/>
		<constructor-arg name="creditCardNumber" value="3557465650724368"/>
	</bean>
	<bean id="153" class="com.kamilradzyminski.projekt.domain.Person">
		<constructor-arg name="id" value="153"/>
		<constructor-arg name="firstName" value="Buffy"/>
		<constructor-arg name="lastName" value="Haselhurst"/>
		<constructor-arg name="email" value="bhaselhurst48@vkontakte.ru"/>
		<constructor-arg name="gender" value="Female"/>
		<constructor-arg name="creditCardType" value="jcb"/>
		<constructor-arg name="creditCardNumber" value="3550519745025012"/>
	</bean>
	<bean id="154" class="com.kamilradzyminski.projekt.domain.Person">
		<constructor-arg name="id" value="154"/>
		<constructor-arg name="firstName" value="Worthy"/>
		<constructor-arg name="lastName" value="Dewi"/>
		<constructor-arg name="email" value="wdewi49@artisteer.com"/>
		<constructor-arg name="gender" value="Male"/>
		<constructor-arg name="creditCardType" value="china-unionpay"/>
		<constructor-arg name="creditCardNumber" value="560223427865823057"/>
	</bean>
	<bean id="155" class="com.kamilradzyminski.projekt.domain.Person">
		<constructor-arg name="id" value="155"/>
		<constructor-arg name="firstName" value="Rhoda"/>
		<constructor-arg name="lastName" value="Mandry"/>
		<constructor-arg name="email" value="rmandry4a@google.com.br"/>
		<constructor-arg name="gender" value="Female"/>
		<constructor-arg name="creditCardType" value="jcb"/>
		<constructor-arg name="creditCardNumber" value="3550612873107122"/>
	</bean>
	<bean id="156" class="com.kamilradzyminski.projekt.domain.Person">
		<constructor-arg name="id" value="156"/>
		<constructor-arg name="firstName" value="Halsey"/>
		<constructor-arg name="lastName" value="Joannet"/>
		<constructor-arg name="email" value="hjoannet4b@house.gov"/>
		<constructor-arg name="gender" value="Male"/>
		<constructor-arg name="creditCardType" value="diners-club-carte-blanche"/>
		<constructor-arg name="creditCardNumber" value="30454254831673"/>
	</bean>
	<bean id="157" class="com.kamilradzyminski.projekt.domain.Person">
		<constructor-arg name="id" value="157"/>
		<constructor-arg name="firstName" value="Maryrose"/>
		<constructor-arg name="lastName" value="Dancy"/>
		<constructor-arg name="email" value="mdancy4c@quantcast.com"/>
		<constructor-arg name="gender" value="Female"/>
		<constructor-arg name="creditCardType" value="instapayment"/>
		<constructor-arg name="creditCardNumber" value="6390352580184091"/>
	</bean>
	<bean id="158" class="com.kamilradzyminski.projekt.domain.Person">
		<constructor-arg name="id" value="158"/>
		<constructor-arg name="firstName" value="Elvin"/>
		<constructor-arg name="lastName" value="Janicki"/>
		<constructor-arg name="email" value="ejanicki4d@redcross.org"/>
		<constructor-arg name="gender" value="Male"/>
		<constructor-arg name="creditCardType" value="diners-club-international"/>
		<constructor-arg name="creditCardNumber" value="36809246469516"/>
	</bean>
	<bean id="159" class="com.kamilradzyminski.projekt.domain.Person">
		<constructor-arg name="id" value="159"/>
		<constructor-arg name="firstName" value="Deerdre"/>
		<constructor-arg name="lastName" value="Drohane"/>
		<constructor-arg name="email" value="ddrohane4e@nba.com"/>
		<constructor-arg name="gender" value="Female"/>
		<constructor-arg name="creditCardType" value="diners-club-carte-blanche"/>
		<constructor-arg name="creditCardNumber" value="30426592801196"/>
	</bean>
	<bean id="160" class="com.kamilradzyminski.projekt.domain.Person">
		<constructor-arg name="id" value="160"/>
		<constructor-arg name="firstName" value="Hersh"/>
		<constructor-arg name="lastName" value="Switzer"/>
		<constructor-arg name="email" value="hswitzer4f@furl.net"/>
		<constructor-arg name="gender" value="Male"/>
		<constructor-arg name="creditCardType" value="visa"/>
		<constructor-arg name="creditCardNumber" value="4041592506140267"/>
	</bean>
	<bean id="161" class="com.kamilradzyminski.projekt.domain.Person">
		<constructor-arg name="id" value="161"/>
		<constructor-arg name="firstName" value="Lamar"/>
		<constructor-arg name="lastName" value="M'Barron"/>
		<constructor-arg name="email" value="lmbarron4g@360.cn"/>
		<constructor-arg name="gender" value="Male"/>
		<constructor-arg name="creditCardType" value="visa-electron"/>
		<constructor-arg name="creditCardNumber" value="4175007470576733"/>
	</bean>
	<bean id="162" class="com.kamilradzyminski.projekt.domain.Person">
		<constructor-arg name="id" value="162"/>
		<constructor-arg name="firstName" value="Claudius"/>
		<constructor-arg name="lastName" value="Arckoll"/>
		<constructor-arg name="email" value="carckoll4h@oracle.com"/>
		<constructor-arg name="gender" value="Male"/>
		<constructor-arg name="creditCardType" value="americanexpress"/>
		<constructor-arg name="creditCardNumber" value="337941990892845"/>
	</bean>
	<bean id="163" class="com.kamilradzyminski.projekt.domain.Person">
		<constructor-arg name="id" value="163"/>
		<constructor-arg name="firstName" value="Aline"/>
		<constructor-arg name="lastName" value="Pane"/>
		<constructor-arg name="email" value="apane4i@live.com"/>
		<constructor-arg name="gender" value="Female"/>
		<constructor-arg name="creditCardType" value="maestro"/>
		<constructor-arg name="creditCardNumber" value="6763386047656348002"/>
	</bean>
	<bean id="164" class="com.kamilradzyminski.projekt.domain.Person">
		<constructor-arg name="id" value="164"/>
		<constructor-arg name="firstName" value="Lutero"/>
		<constructor-arg name="lastName" value="Bicksteth"/>
		<constructor-arg name="email" value="lbicksteth4j@home.pl"/>
		<constructor-arg name="gender" value="Male"/>
		<constructor-arg name="creditCardType" value="maestro"/>
		<constructor-arg name="creditCardNumber" value="676224363889338967"/>
	</bean>
	<bean id="165" class="com.kamilradzyminski.projekt.domain.Person">
		<constructor-arg name="id" value="165"/>
		<constructor-arg name="firstName" value="Mae"/>
		<constructor-arg name="lastName" value="Hadcroft"/>
		<constructor-arg name="email" value="mhadcroft4k@bloglovin.com"/>
		<constructor-arg name="gender" value="Female"/>
		<constructor-arg name="creditCardType" value="mastercard"/>
		<constructor-arg name="creditCardNumber" value="5010123784834662"/>
	</bean>
	<bean id="166" class="com.kamilradzyminski.projekt.domain.Person">
		<constructor-arg name="id" value="166"/>
		<constructor-arg name="firstName" value="Inness"/>
		<constructor-arg name="lastName" value="Saurat"/>
		<constructor-arg name="email" value="isaurat4l@issuu.com"/>
		<constructor-arg name="gender" value="Male"/>
		<constructor-arg name="creditCardType" value="jcb"/>
		<constructor-arg name="creditCardNumber" value="3557527410499811"/>
	</bean>
	<bean id="167" class="com.kamilradzyminski.projekt.domain.Person">
		<constructor-arg name="id" value="167"/>
		<constructor-arg name="firstName" value="Hector"/>
		<constructor-arg name="lastName" value="Zaniolini"/>
		<constructor-arg name="email" value="hzaniolini4m@hp.com"/>
		<constructor-arg name="gender" value="Male"/>
		<constructor-arg name="creditCardType" value="jcb"/>
		<constructor-arg name="creditCardNumber" value="3575660442175402"/>
	</bean>
	<bean id="168" class="com.kamilradzyminski.projekt.domain.Person">
		<constructor-arg name="id" value="168"/>
		<constructor-arg name="firstName" value="Joanne"/>
		<constructor-arg name="lastName" value="Lokier"/>
		<constructor-arg name="email" value="jlokier4n@arstechnica.com"/>
		<constructor-arg name="gender" value="Female"/>
		<constructor-arg name="creditCardType" value="jcb"/>
		<constructor-arg name="creditCardNumber" value="3544070850635962"/>
	</bean>
	<bean id="169" class="com.kamilradzyminski.projekt.domain.Person">
		<constructor-arg name="id" value="169"/>
		<constructor-arg name="firstName" value="Mordy"/>
		<constructor-arg name="lastName" value="Doucette"/>
		<constructor-arg name="email" value="mdoucette4o@dmoz.org"/>
		<constructor-arg name="gender" value="Male"/>
		<constructor-arg name="creditCardType" value="diners-club-us-ca"/>
		<constructor-arg name="creditCardNumber" value="5410523001460694"/>
	</bean>
	<bean id="170" class="com.kamilradzyminski.projekt.domain.Person">
		<constructor-arg name="id" value="170"/>
		<constructor-arg name="firstName" value="Tabitha"/>
		<constructor-arg name="lastName" value="Eykel"/>
		<constructor-arg name="email" value="teykel4p@github.com"/>
		<constructor-arg name="gender" value="Female"/>
		<constructor-arg name="creditCardType" value="diners-club-enroute"/>
		<constructor-arg name="creditCardNumber" value="201408120080538"/>
	</bean>
	<bean id="171" class="com.kamilradzyminski.projekt.domain.Person">
		<constructor-arg name="id" value="171"/>
		<constructor-arg name="firstName" value="Angus"/>
		<constructor-arg name="lastName" value="Rickeard"/>
		<constructor-arg name="email" value="arickeard4q@mit.edu"/>
		<constructor-arg name="gender" value="Male"/>
		<constructor-arg name="creditCardType" value="jcb"/>
		<constructor-arg name="creditCardNumber" value="3564613641708054"/>
	</bean>
	<bean id="172" class="com.kamilradzyminski.projekt.domain.Person">
		<constructor-arg name="id" value="172"/>
		<constructor-arg name="firstName" value="Gleda"/>
		<constructor-arg name="lastName" value="Hempshall"/>
		<constructor-arg name="email" value="ghempshall4r@google.ca"/>
		<constructor-arg name="gender" value="Female"/>
		<constructor-arg name="creditCardType" value="diners-club-enroute"/>
		<constructor-arg name="creditCardNumber" value="201541885845339"/>
	</bean>
	<bean id="173" class="com.kamilradzyminski.projekt.domain.Person">
		<constructor-arg name="id" value="173"/>
		<constructor-arg name="firstName" value="Hayyim"/>
		<constructor-arg name="lastName" value="Brunotti"/>
		<constructor-arg name="email" value="hbrunotti4s@etsy.com"/>
		<constructor-arg name="gender" value="Male"/>
		<constructor-arg name="creditCardType" value="diners-club-carte-blanche"/>
		<constructor-arg name="creditCardNumber" value="30000901042519"/>
	</bean>
	<bean id="174" class="com.kamilradzyminski.projekt.domain.Person">
		<constructor-arg name="id" value="174"/>
		<constructor-arg name="firstName" value="Brose"/>
		<constructor-arg name="lastName" value="Jerger"/>
		<constructor-arg name="email" value="bjerger4t@opera.com"/>
		<constructor-arg name="gender" value="Male"/>
		<constructor-arg name="creditCardType" value="jcb"/>
		<constructor-arg name="creditCardNumber" value="3536208798182776"/>
	</bean>
	<bean id="175" class="com.kamilradzyminski.projekt.domain.Person">
		<constructor-arg name="id" value="175"/>
		<constructor-arg name="firstName" value="Derick"/>
		<constructor-arg name="lastName" value="Tallman"/>
		<constructor-arg name="email" value="dtallman4u@guardian.co.uk"/>
		<constructor-arg name="gender" value="Male"/>
		<constructor-arg name="creditCardType" value="laser"/>
		<constructor-arg name="creditCardNumber" value="6709972830860293"/>
	</bean>
	<bean id="176" class="com.kamilradzyminski.projekt.domain.Person">
		<constructor-arg name="id" value="176"/>
		<constructor-arg name="firstName" value="Kimberly"/>
		<constructor-arg name="lastName" value="Lodwick"/>
		<constructor-arg name="email" value="klodwick4v@newsvine.com"/>
		<constructor-arg name="gender" value="Female"/>
		<constructor-arg name="creditCardType" value="jcb"/>
		<constructor-arg name="creditCardNumber" value="3552535954882784"/>
	</bean>
	<bean id="177" class="com.kamilradzyminski.projekt.domain.Person">
		<constructor-arg name="id" value="177"/>
		<constructor-arg name="firstName" value="Bendix"/>
		<constructor-arg name="lastName" value="Kennermann"/>
		<constructor-arg name="email" value="bkennermann4w@alexa.com"/>
		<constructor-arg name="gender" value="Male"/>
		<constructor-arg name="creditCardType" value="jcb"/>
		<constructor-arg name="creditCardNumber" value="3559159054440204"/>
	</bean>
	<bean id="178" class="com.kamilradzyminski.projekt.domain.Person">
		<constructor-arg name="id" value="178"/>
		<constructor-arg name="firstName" value="Markos"/>
		<constructor-arg name="lastName" value="Celloni"/>
		<constructor-arg name="email" value="mcelloni4x@google.cn"/>
		<constructor-arg name="gender" value="Male"/>
		<constructor-arg name="creditCardType" value="switch"/>
		<constructor-arg name="creditCardNumber" value="6759455095637944"/>
	</bean>
	<bean id="179" class="com.kamilradzyminski.projekt.domain.Person">
		<constructor-arg name="id" value="179"/>
		<constructor-arg name="firstName" value="Harley"/>
		<constructor-arg name="lastName" value="Yeats"/>
		<constructor-arg name="email" value="hyeats4y@jiathis.com"/>
		<constructor-arg name="gender" value="Male"/>
		<constructor-arg name="creditCardType" value="diners-club-enroute"/>
		<constructor-arg name="creditCardNumber" value="201851290726960"/>
	</bean>
	<bean id="180" class="com.kamilradzyminski.projekt.domain.Person">
		<constructor-arg name="id" value="180"/>
		<constructor-arg name="firstName" value="Raychel"/>
		<constructor-arg name="lastName" value="MacKilroe"/>
		<constructor-arg name="email" value="rmackilroe4z@wufoo.com"/>
		<constructor-arg name="gender" value="Female"/>
		<constructor-arg name="creditCardType" value="jcb"/>
		<constructor-arg name="creditCardNumber" value="3575978821121387"/>
	</bean>
	<bean id="181" class="com.kamilradzyminski.projekt.domain.Person">
		<constructor-arg name="id" value="181"/>
		<constructor-arg name="firstName" value="Batsheva"/>
		<constructor-arg name="lastName" value="Niese"/>
		<constructor-arg name="email" value="bniese50@free.fr"/>
		<constructor-arg name="gender" value="Female"/>
		<constructor-arg name="creditCardType" value="jcb"/>
		<constructor-arg name="creditCardNumber" value="3564671156071680"/>
	</bean>
	<bean id="182" class="com.kamilradzyminski.projekt.domain.Person">
		<constructor-arg name="id" value="182"/>
		<constructor-arg name="firstName" value="Roze"/>
		<constructor-arg name="lastName" value="Collishaw"/>
		<constructor-arg name="email" value="rcollishaw51@alibaba.com"/>
		<constructor-arg name="gender" value="Female"/>
		<constructor-arg name="creditCardType" value="instapayment"/>
		<constructor-arg name="creditCardNumber" value="6395915487303439"/>
	</bean>
	<bean id="183" class="com.kamilradzyminski.projekt.domain.Person">
		<constructor-arg name="id" value="183"/>
		<constructor-arg name="firstName" value="Garfield"/>
		<constructor-arg name="lastName" value="Slaten"/>
		<constructor-arg name="email" value="gslaten52@webmd.com"/>
		<constructor-arg name="gender" value="Male"/>
		<constructor-arg name="creditCardType" value="laser"/>
		<constructor-arg name="creditCardNumber" value="6771641224880015350"/>
	</bean>
	<bean id="184" class="com.kamilradzyminski.projekt.domain.Person">
		<constructor-arg name="id" value="184"/>
		<constructor-arg name="firstName" value="Matias"/>
		<constructor-arg name="lastName" value="Conboy"/>
		<constructor-arg name="email" value="mconboy53@webs.com"/>
		<constructor-arg name="gender" value="Male"/>
		<constructor-arg name="creditCardType" value="mastercard"/>
		<constructor-arg name="creditCardNumber" value="5002353577803638"/>
	</bean>
	<bean id="185" class="com.kamilradzyminski.projekt.domain.Person">
		<constructor-arg name="id" value="185"/>
		<constructor-arg name="firstName" value="Wally"/>
		<constructor-arg name="lastName" value="Penswick"/>
		<constructor-arg name="email" value="wpenswick54@gizmodo.com"/>
		<constructor-arg name="gender" value="Female"/>
		<constructor-arg name="creditCardType" value="jcb"/>
		<constructor-arg name="creditCardNumber" value="3534561232241075"/>
	</bean>
	<bean id="186" class="com.kamilradzyminski.projekt.domain.Person">
		<constructor-arg name="id" value="186"/>
		<constructor-arg name="firstName" value="Brian"/>
		<constructor-arg name="lastName" value="Zapata"/>
		<constructor-arg name="email" value="bzapata55@woothemes.com"/>
		<constructor-arg name="gender" value="Male"/>
		<constructor-arg name="creditCardType" value="visa-electron"/>
		<constructor-arg name="creditCardNumber" value="4026354467123025"/>
	</bean>
	<bean id="187" class="com.kamilradzyminski.projekt.domain.Person">
		<constructor-arg name="id" value="187"/>
		<constructor-arg name="firstName" value="Julita"/>
		<constructor-arg name="lastName" value="Cassimer"/>
		<constructor-arg name="email" value="jcassimer56@princeton.edu"/>
		<constructor-arg name="gender" value="Female"/>
		<constructor-arg name="creditCardType" value="jcb"/>
		<constructor-arg name="creditCardNumber" value="3551947926154344"/>
	</bean>
	<bean id="188" class="com.kamilradzyminski.projekt.domain.Person">
		<constructor-arg name="id" value="188"/>
		<constructor-arg name="firstName" value="Siegfried"/>
		<constructor-arg name="lastName" value="McCaughren"/>
		<constructor-arg name="email" value="smccaughren57@sohu.com"/>
		<constructor-arg name="gender" value="Male"/>
		<constructor-arg name="creditCardType" value="switch"/>
		<constructor-arg name="creditCardNumber" value="4905009424765708"/>
	</bean>
	<bean id="189" class="com.kamilradzyminski.projekt.domain.Person">
		<constructor-arg name="id" value="189"/>
		<constructor-arg name="firstName" value="Walther"/>
		<constructor-arg name="lastName" value="Du Barry"/>
		<constructor-arg name="email" value="wdubarry58@vistaprint.com"/>
		<constructor-arg name="gender" value="Male"/>
		<constructor-arg name="creditCardType" value="jcb"/>
		<constructor-arg name="creditCardNumber" value="3532592078124416"/>
	</bean>
	<bean id="190" class="com.kamilradzyminski.projekt.domain.Person">
		<constructor-arg name="id" value="190"/>
		<constructor-arg name="firstName" value="Barty"/>
		<constructor-arg name="lastName" value="Knowlman"/>
		<constructor-arg name="email" value="bknowlman59@icio.us"/>
		<constructor-arg name="gender" value="Male"/>
		<constructor-arg name="creditCardType" value="jcb"/>
		<constructor-arg name="creditCardNumber" value="3556056844232524"/>
	</bean>
	<bean id="191" class="com.kamilradzyminski.projekt.domain.Person">
		<constructor-arg name="id" value="191"/>
		<constructor-arg name="firstName" value="Stanly"/>
		<constructor-arg name="lastName" value="Francioli"/>
		<constructor-arg name="email" value="sfrancioli5a@slate.com"/>
		<constructor-arg name="gender" value="Male"/>
		<constructor-arg name="creditCardType" value="switch"/>
		<constructor-arg name="creditCardNumber" value="493612318260511178"/>
	</bean>
	<bean id="192" class="com.kamilradzyminski.projekt.domain.Person">
		<constructor-arg name="id" value="192"/>
		<constructor-arg name="firstName" value="Freda"/>
		<constructor-arg name="lastName" value="Linneman"/>
		<constructor-arg name="email" value="flinneman5b@creativecommons.org"/>
		<constructor-arg name="gender" value="Female"/>
		<constructor-arg name="creditCardType" value="jcb"/>
		<constructor-arg name="creditCardNumber" value="3588080287839530"/>
	</bean>
	<bean id="193" class="com.kamilradzyminski.projekt.domain.Person">
		<constructor-arg name="id" value="193"/>
		<constructor-arg name="firstName" value="Pauly"/>
		<constructor-arg name="lastName" value="Wait"/>
		<constructor-arg name="email" value="pwait5c@live.com"/>
		<constructor-arg name="gender" value="Male"/>
		<constructor-arg name="creditCardType" value="mastercard"/>
		<constructor-arg name="creditCardNumber" value="5048372950631586"/>
	</bean>
	<bean id="194" class="com.kamilradzyminski.projekt.domain.Person">
		<constructor-arg name="id" value="194"/>
		<constructor-arg name="firstName" value="Daveta"/>
		<constructor-arg name="lastName" value="McCusker"/>
		<constructor-arg name="email" value="dmccusker5d@un.org"/>
		<constructor-arg name="gender" value="Female"/>
		<constructor-arg name="creditCardType" value="mastercard"/>
		<constructor-arg name="creditCardNumber" value="5209489079909670"/>
	</bean>
	<bean id="195" class="com.kamilradzyminski.projekt.domain.Person">
		<constructor-arg name="id" value="195"/>
		<constructor-arg name="firstName" value="Beryl"/>
		<constructor-arg name="lastName" value="Biset"/>
		<constructor-arg name="email" value="bbiset5e@arstechnica.com"/>
		<constructor-arg name="gender" value="Female"/>
		<constructor-arg name="creditCardType" value="mastercard"/>
		<constructor-arg name="creditCardNumber" value="5100179789099116"/>
	</bean>
	<bean id="196" class="com.kamilradzyminski.projekt.domain.Person">
		<constructor-arg name="id" value="196"/>
		<constructor-arg name="firstName" value="Padraic"/>
		<constructor-arg name="lastName" value="Janisson"/>
		<constructor-arg name="email" value="pjanisson5f@umn.edu"/>
		<constructor-arg name="gender" value="Male"/>
		<constructor-arg name="creditCardType" value="bankcard"/>
		<constructor-arg name="creditCardNumber" value="5602250100060229"/>
	</bean>
	<bean id="197" class="com.kamilradzyminski.projekt.domain.Person">
		<constructor-arg name="id" value="197"/>
		<constructor-arg name="firstName" value="Jayne"/>
		<constructor-arg name="lastName" value="Ranken"/>
		<constructor-arg name="email" value="jranken5g@ustream.tv"/>
		<constructor-arg name="gender" value="Female"/>
		<constructor-arg name="creditCardType" value="china-unionpay"/>
		<constructor-arg name="creditCardNumber" value="56022461242948800"/>
	</bean>
	<bean id="198" class="com.kamilradzyminski.projekt.domain.Person">
		<constructor-arg name="id" value="198"/>
		<constructor-arg name="firstName" value="Davon"/>
		<constructor-arg name="lastName" value="Morteo"/>
		<constructor-arg name="email" value="dmorteo5h@bbb.org"/>
		<constructor-arg name="gender" value="Male"/>
		<constructor-arg name="creditCardType" value="mastercard"/>
		<constructor-arg name="creditCardNumber" value="5048372174545117"/>
	</bean>
	<bean id="199" class="com.kamilradzyminski.projekt.domain.Person">
		<constructor-arg name="id" value="199"/>
		<constructor-arg name="firstName" value="Irv"/>
		<constructor-arg name="lastName" value="Grenkov"/>
		<constructor-arg name="email" value="igrenkov5i@biglobe.ne.jp"/>
		<constructor-arg name="gender" value="Male"/>
		<constructor-arg name="creditCardType" value="diners-club-enroute"/>
		<constructor-arg name="creditCardNumber" value="201870992816754"/>
	</bean>
</beans>